Workbook

Sheet qsr_pos_logs_Uncleaned
A1: order_id | B1: store_id | C1: transaction_datetime | D1: business_day | E1: daypart | F1: service_mode | G1: menu_item | H1: modifier | I1: quantity | J1: unit_price | K1: discount | L1: tax | M1: total_amount | N1: payment_type
A2: 120000 | B2: 102 | C2: 45843.26 | D2: 45843 | E2: Breakfast | F2: Drive-Thru | G2: Bottled Water | I2: 1 | J2: 1.48 | K2: 0.15 | L2: 0.1 | M2: 1.43 | N2: Cash
A3: 120001 | B3: 201 | C3: 45843.492 | D3: 45843 | E3: Lunch | F3: Dine-In | G3: Chicken Sandwich | I3: 1 | J3: 5.34 | K3: 0 | L3: 0.45 | M3: 5.79 | N3: Card
A4: 120002 | B4: 403 | C4: 45760.337 | D4: 45760 | E4: Breakfast | F4: Takeout | G4: Bottled Water | H4: Light Ice | I4: 1 | J4: 1.49 | K4: 0.15 | L4: 0.1 | M4: 1.44 | N4: Cash
A5: 120003 | B5: 301 | C5: 45833.279 | D5: 45833 | E5: Breakfast | F5: Drive-Thru | G5: Egg Muffin | H5: No Cheese | I5: 1 | J5: 3.62 | K5: 0 | L5: 0.34 | M5: 3.96 | N5: Cash
A6: 120004 | B6: 301 | C6: 45870.541 | D6: 45870 | E6: Lunch | F6: Drive-Thru | G6: Spicy Chicken Combo | I6: 2 | J6: 9.17 | K6: 0 | L6: 1.38 | M6: 19.72 | N6: Card
A7: 120005 | B7: 501 | C7: 45850.523 | D7: 45850 | E7: Lunch | F7: Dine-In | G7: Double Cheeseburger | I7: 1 | J7: 5.64 | K7: 0 | L7: 0.37 | M7: 6.01 | N7: Card
A8: 120006 | B8: 101 | C8: 45864.748 | D8: 45864 | E8: Afternoon | F8: Delivery | G8: Onion Rings | I8: 1 | J8: 3.59 | K8: 0.54 | L8: 0.29 | M8: 3.34 | N8: MobilePay
A9: 120007 | B9: 403 | C9: 45859.7 | D9: 45859 | E9: Afternoon | F9: Takeout | G9: Soft Drink (Medium) | I9: 1 | J9: 1.8 | K9: 0.27 | L9: 0.11 | M9: 1.64 | N9: Cash
A10: 120008 | B10: 102 | C10: 45810.964 | D10: 45810 | E10: Late Night | F10: Delivery | G10: Chicken Sandwich | H10: Extra Sauce | I10: 2 | J10: 5.22 | K10: 0 | L10: 0.79 | M10: 11.73 | N10: Card
A11: 120009 | B11: 402 | C11: 45850.223 | D11: 45850 | E11: Breakfast | F11: Drive-Thru | G11: Hash Browns | I11: 1 | J11: 2 | K11: 0 | L11: 0.12 | M11: 2.12 | N11: Card
A12: 120010 | B12: 103 | C12: 45766.886 | D12: 45766 | E12: Dinner | F12: Takeout | G12: Double Cheeseburger | I12: 1 | J12: 5.55 | K12: 0 | L12: 0.33 | M12: 5.88 | N12: Card
A13: 120011 | B13: 102 | C13: 45854.464 | D13: 45854 | E13: Morning | F13: Dine-In | G13: Apple Pie | I13: 1 | J13: 1.53 | K13: 0 | L13: 0.1 | M13: 1.63 | N13: Card
A14: 120012 | B14: 201 | C14: 45816.343 | D14: 45816 | E14: Breakfast | F14: Takeout | G14: Sausage Biscuit | H14: Sausage Patty | I14: 2 | J14: 3.1 | K14: 0 | L14: 0.64 | M14: 9.24 | N14: Card
A15: 120013 | B15: 103 | C15: 45851.443 | D15: 45851 | E15: Morning | F15: Takeout | G15: Coffee | H15: Oat Milk | I15: 2 | J15: 1.51 | K15: 0 | L15: 0.27 | M15: 4.69 | N15: Cash
A16: 120014 | B16: 201 | C16: 45758.526 | D16: 45758 | E16: Lunch | F16: Dine-In | G16: Spicy Chicken Combo | I16: 1 | J16: 8.43 | K16: 0 | L16: 0.67 | M16: 9.1 | N16: Card
A17: 120015 | B17: 102 | C17: 45799.379 | D17: 45799 | E17: Breakfast | F17: Delivery | G17: Egg Muffin | I17: 1 | J17: 3.1 | K17: 0 | L17: 0.23 | M17: 3.33 | N17: Card
A18: 120016 | B18: 403 | C18: 45774.389 | D18: 45774 | E18: Breakfast | F18: Drive-Thru | G18: Egg Muffin | I18: 1 | J18: 2.99 | K18: 0 | L18: 0.22 | M18: 3.21 | N18: MobilePay
A19: 120017 | B19: 403 | C19: 45763.462 | D19: 45763 | E19: Lunch | F19: Takeout | G19: Cheeseburger | I19: 1 | J19: 4.59 | K19: 0 | M19: 5 | N19: Card
A20: 120018 | B20: 403 | C20: 45831.399 | D20: 45831 | E20: Breakfast | F20: Takeout | G20: Sausage Biscuit | H20: Extra Egg | I20: 2 | J20: 2.81 | K20: 0 | L20: 0.55 | M20: 8.17 | N20: Card
A21: 120019 | B21: 103 | C21: 45848.828 | D21: 45848 | E21: Dinner | F21: Dine-In | G21: Chicken Sandwich | H21: Extra Sauce | I21: 1 | J21: 4.87 | K21: 0 | L21: 0.37 | M21: 5.49 | N21: Card
A22: 120020 | B22: 201 | C22: 45761.474 | D22: 45761 | E22: Morning | F22: Drive-Thru | G22: Coffee | H22: Sugar-Free Syrup | I22: 1 | J22: 2.18 | K22: 0 | L22: 0.19 | M22: 2.67 | N22: MobilePay
A23: 120021 | B23: 101 | C23: 45845.276 | D23: 45845 | E23: Breakfast | F23: Dine-In | G23: Sausage Biscuit | H23: Cinnamon | I23: 1 | J23: 2.98 | K23: 0 | L23: 0.26 | M23: 3.34 | N23: Cash
A24: 120022 | B24: 403 | C24: 45758.741 | D24: 45758 | E24: Afternoon | F24: Dine-In | G24: Ice Cream Cone | H24: Cinnamon | I24: 1 | J24: 1.65 | K24: 0 | L24: 0.13 | M24: 1.88 | N24: Card
A25: 120023 | B25: 201 | C25: 45758.614 | D25: 45758 | E25: Lunch | F25: Drive-Thru | G25: Spicy Chicken Sandwich | H25: No Pickles | I25: 1 | J25: 5.09 | K25: 0 | L25: 0.41 | M25: 5.5 | N25: Cash
A26: 120024 | B26: 103 | C26: 45842.738 | D26: 45842 | E26: Afternoon | F26: Takeout | G26: Ice Cream Cone | I26: 1 | J26: 1.58 | K26: 0 | L26: 0.11 | M26: 1.69 | N26: Card
A27: 120025 | B27: 401 | C27: 45805.823 | D27: 45805 | E27: Dinner | F27: Takeout | G27: Chicken Sandwich | H27: Extra Cheese | I27: 1 | J27: 5.43 | K27: 0 | L27: 0.56 | M27: 6.49 | N27: Card
A28: 120026 | B28: 402 | C28: 45807.723 | D28: 45807 | E28: Afternoon | F28: Drive-Thru | G28: Milkshake | H28: Cinnamon | I28: 1 | J28: 3.61 | K28: 0 | L28: 0.33 | M28: 4.04 | N28: Cash
A29: 120027 | B29: 402 | C29: 45843.67 | D29: 45843 | E29: Afternoon | F29: Dine-In | G29: French Fries | H29: Small Size | I29: 1 | J29: 2.75 | K29: 0 | L29: 0.17 | M29: 2.62 | N29: Card
A30: 120028 | B30: 201 | C30: 45829.788 | D30: 45829 | E30: Dinner | F30: Drive-Thru | G30: Cheeseburger | I30: 1 | J30: 4.29 | K30: 0 | L30: 0.36 | M30: 4.65 | N30: Card
A31: 120029 | B31: 202 | C31: 45875.598 | D31: 45875 | E31: Lunch | F31: Delivery | G31: Chicken Sandwich | H31: No Onions | I31: 3 | J31: 5.28 | K31: 0 | L31: 1.35 | M31: 17.19 | N31: Card
A32: 120030 | B32: 103 | C32: 45830.301 | D32: 45830 | E32: Breakfast | F32: Takeout | G32: Sausage Biscuit | I32: 1 | J32: 2.89 | K32: 0.15 | L32: 0.27 | M32: 3.11 | N32: Cash
A33: 120031 | B33: 101 | C33: 45847.828 | D33: 45847 | E33: Dinner | F33: Delivery | G33: Cheeseburger Combo | I33: 2 | J33: 9.42 | K33: 0 | L33: 1.41 | M33: 20.25 | N33: Card
A34: 120032 | B34: 103 | C34: 45865.958 | D34: 45865 | E34: Late Night | F34: Drive-Thru | G34: Spicy Chicken Sandwich | I34: 1 | J34: 5.63 | K34: 0 | L34: 0.48 | M34: 7.11 | N34: MobilePay
A35: 120033 | B35: 501 | C35: 45834.904 | D35: 45834 | E35: Dinner | F35: Dine-In | G35: Cheeseburger | I35: 1 | J35: 4.14 | K35: 0 | L35: 0.33 | M35: 4.47 | N35: Cash
A36: 120034 | B36: 202 | C36: 45761.743 | D36: 45761 | E36: Afternoon | F36: Takeout | G36: Iced Tea | I36: 1 | J36: 2 | K36: 0 | L36: 0.15 | M36: 2.15 | N36: MobilePay
A37: 120035 | B37: 101 | C37: 45837.522 | D37: 45837 | E37: Lunch | F37: Takeout | G37: Chicken Sandwich | I37: 1 | J37: 4.94 | K37: 0 | L37: 0.43 | M37: 6.37 | N37: Card
A38: 120036 | B38: 402 | C38: 45876.471 | D38: 45876 | E38: Lunch | F38: Takeout | G38: Spicy Chicken Combo | I38: 1 | J38: 9.39 | K38: 0 | L38: 0.89 | M38: 10.28 | N38: Card
A39: 120037 | B39: 201 | C39: 45783.508 | D39: 45783 | E39: Lunch | F39: Drive-Thru | G39: Chicken Sandwich Combo | H39: Spicy | I39: 1 | J39: 8.01 | K39: 0 | L39: 0.58 | M39: 8.59 | N39: Card
A40: 120038 | B40: 101 | C40: 45808.031 | D40: 45808 | E40: Late Night | F40: Drive-Thru | G40: Cheeseburger | I40: 1 | J40: 4.05 | K40: 0 | L40: 0.32 | M40: 4.37 | N40: Cash
A41: 120039 | B41: 401 | C41: 45805.465 | D41: 45805 | E41: Lunch | F41: Drive-Thru | G41: Cheeseburger | I41: 1 | J41: 4.56 | K41: 0 | L41: 0.33 | M41: 4.89 | N41: MobilePay
A42: 120040 | B42: 401 | C42: 45799.486 | D42: 45799 | E42: Lunch | F42: Dine-In | G42: Chicken Sandwich Combo | I42: 1 | J42: 9.36 | K42: 0 | L42: 0.89 | M42: 10.25
A43: 120041 | B43: 201 | C43: 45842.587 | D43: 45842 | E43: Lunch | F43: Dine-In | G43: Double Cheeseburger Combo | I43: 1 | J43: 10.08 | K43: 0 | L43: 0.66 | M43: 10.74 | N43: Card
A44: 120042 | B44: 103 | C44: 45802.853 | D44: 45802 | E44: Dinner | F44: Takeout | G44: Cheeseburger Combo | I44: 1 | J44: 8.43 | K44: 0 | L44: 0.51 | M44: 8.94 | N44: Card
A45: 120043 | B45: 501 | C45: 45876.745 | D45: 45876 | E45: Afternoon | F45: Takeout | G45: Chicken Nuggets (10pc) | I45: 1 | J45: 4.89 | K45: 0 | L45: 0.42 | M45: 5.31 | N45: Cash
A46: 120044 | B46: 102 | C46: 45836.906 | D46: 45836 | E46: Dinner | G46: Double Cheeseburger Combo | I46: 1 | J46: 9.25 | K46: 0 | L46: 0.74 | M46: 9.99 | N46: MobilePay
A47: 120045 | B47: 403 | C47: 45872.523 | D47: 45872 | E47: Lunch | F47: Delivery | G47: Cheeseburger Combo | I47: 1 | J47: 8.13 | K47: 0 | L47: 0.61 | M47: 8.74 | N47: Card
A48: 120046 | B48: 201 | C48: 45839.775 | D48: 45839 | E48: Dinner | F48: Dine-In | G48: Onion Rings | H48: Large Size | I48: 1 | J48: 3.01 | K48: 0 | L48: 0.27 | M48: 3.88 | N48: GiftCard
A49: 120047 | B49: 403 | C49: 45854.398 | D49: 45854 | E49: Breakfast | F49: Drive-Thru | G49: Hash Browns | H49: Cinnamon | I49: 1 | J49: 2.1 | K49: 0 | L49: 0.16 | M49: 2.36 | N49: MobilePay
A50: 120048 | B50: 402 | C50: 45821.891 | D50: 45821 | E50: Dinner | F50: Delivery | G50: Cheeseburger Combo | I50: 1 | J50: 8.66 | K50: 0 | L50: 0.74 | M50: 9.4 | N50: Card
A51: 120049 | B51: 401 | C51: 45794.522 | D51: 45794 | E51: Lunch | F51: Dine-In | G51: Spicy Chicken Sandwich | I51: 2 | J51: 4.96 | K51: 1.98 | L51: 0.48 | M51: 8.42 | N51: GiftCard
A52: 120050 | B52: 202 | C52: 45790.612 | D52: 45790 | E52: Lunch | F52: Drive-Thru | G52: French Fries | H52: No Sauce | I52: 1 | J52: 2.73 | K52: 0 | L52: 0.25 | M52: 2.98 | N52: MobilePay
A53: 120051 | B53: 201 | C53: 45823.784 | D53: 45823 | E53: Dinner | F53: Delivery | G53: Chicken Sandwich | I53: 1 | J53: 5.25 | K53: 0 | L53: 0.32 | M53: 5.57 | N53: Card
A54: 120052 | B54: 103 | C54: 45868.413 | D54: 45868 | E54: Breakfast | F54: Drive-Thru | G54: Soft Drink (Small) | I54: 1 | J54: 1.48 | K54: 0 | L54: 0.11 | M54: 1.59 | N54: Card
A55: 120053 | B55: 102 | C55: 45834.57 | D55: 45834 | E55: Lunch | F55: Delivery | G55: Spicy Chicken Sandwich | H55: Extra Patty | I55: 1 | J55: 5.87 | K55: 0 | L55: 0.63 | M55: 8.5 | N55: Card
A56: 120054 | B56: 202 | C56: 45768.451 | D56: 45768 | E56: Breakfast | F56: Drive-Thru | G56: Coffee | H56: Extra Ice | I56: 1 | J56: 2.1 | K56: 0 | L56: 0.17 | M56: 2.27 | N56: MobilePay
A57: 120055 | B57: 103 | C57: 45763.737 | D57: 45763 | E57: Afternoon | F57: Takeout | G57: Iced Tea | I57: 2 | J57: 2.01 | K57: 0 | L57: 0.34 | M57: 4.36 | N57: Card
A58: 120056 | B58: 202 | C58: 45846.911 | D58: 45846 | E58: Dinner | F58: Drive-Thru | G58: Double Cheeseburger | I58: 1 | J58: 5.39 | K58: 0 | L58: 0.46 | M58: 5.85 | N58: Card
A59: 120057 | B59: 403 | C59: 45831.45 | D59: 45831 | E59: Breakfast | F59: Takeout | G59: Pancake Platter | H59: No Cheese | I59: 1 | J59: 4.89 | K59: 0 | L59: 0.46 | M59: 5.35 | N59: Card
A60: 120058 | B60: 202 | C60: 45864.626 | D60: 45864 | E60: Afternoon | F60: Takeout | G60: Chicken Nuggets (6pc) | I60: 1 | J60: 3.82 | K60: 0 | L60: 0.36 | M60: 4.18 | N60: Card
A61: 120059 | B61: 402 | C61: 45758.669 | D61: 45758 | E61: Afternoon | F61: Takeout | G61: Ice Cream Cone | I61: 3 | J61: 1.75 | K61: 0 | L61: 0.54 | M61: 7.29 | N61: Card
A62: 120060 | B62: 102 | C62: 45796.735 | D62: 45796 | E62: Afternoon | F62: Dine-In | G62: Ice Cream Cone | H62: Caramel Topping | I62: 1 | J62: 1.58 | K62: 0 | L62: 0.15 | M62: 2.23 | N62: Card
A63: 120061 | B63: 501 | C63: 45769.256 | D63: 45769 | E63: Breakfast | F63: Takeout | G63: Pancake Platter | I63: 1 | J63: 4.93 | K63: 0 | L63: 0.36 | M63: 5.29
A64: 120062 | B64: 102 | C64: 45818.909 | D64: 45818 | E64: Dinner | F64: Takeout | G64: Cheeseburger Combo | I64: 1 | J64: 7.94 | K64: 0 | L64: 0.75 | M64: 8.69 | N64: Card
A65: 120063 | B65: 401 | C65: 45816.749 | D65: 45816 | E65: Afternoon | F65: Dine-In | G65: Iced Tea | I65: 1 | J65: 1.73 | K65: 0 | L65: 0.16 | M65: 1.89 | N65: Card
A66: 120064 | B66: 401 | C66: 45789.246 | D66: 45789 | E66: Breakfast | F66: Drive-Thru | G66: Coffee | I66: 1 | J66: 2.05 | K66: 0 | L66: 0.16 | M66: 2.21 | N66: Cash
A67: 120065 | B67: 202 | C67: 45859.586 | D67: 45859 | E67: Lunch | F67: Drive-Thru | G67: Cheeseburger | I67: 1 | J67: 4.94 | K67: 0 | L67: 0.47 | M67: 5.41 | N67: Card
A68: 120066 | B68: 401 | C68: 45786.763 | D68: 45786 | E68: Dinner | F68: Dine-In | G68: Cheeseburger Combo | I68: 1 | J68: 8.45 | K68: 0 | L68: 0.68 | M68: 9.13 | N68: Card
A69: 120067 | B69: 403 | C69: 45774.944 | D69: 45774 | E69: Late Night | F69: Drive-Thru | G69: Cheeseburger | I69: 1 | J69: 4.82 | K69: 0 | L69: 0.39 | M69: 5.21 | N69: Cash
A70: 120068 | B70: 101 | C70: 45811.267 | D70: 45811 | E70: Breakfast | F70: Takeout | G70: Sausage Biscuit | I70: 2 | J70: 3.13 | K70: 0 | L70: 0.38 | M70: 6.64 | N70: Card
A71: 120069 | B71: 401 | C71: 45822.595 | D71: 45822 | E71: Lunch | F71: Drive-Thru | G71: Cheeseburger Combo | I71: 1 | J71: 8.17 | L71: 0.61 | M71: 8.78 | N71: Card
A72: 120070 | B72: 201 | C72: 45781.846 | D72: 45781 | E72: Dinner | F72: Dine-In | G72: Cheeseburger Combo | I72: 1 | J72: 8.67 | K72: 0 | L72: 0.82 | M72: 9.49 | N72: Card
A73: 120071 | B73: 101 | C73: 45869.567 | D73: 45869 | E73: Lunch | F73: Takeout | G73: Cheeseburger Combo | I73: 1 | J73: 9.26 | K73: 0 | L73: 0.83 | M73: 10.09 | N73: Cash
A74: 120072 | B74: 501 | C74: 45868.622 | D74: 45868 | E74: Lunch | F74: Drive-Thru | G74: Double Cheeseburger Combo | I74: 1 | J74: 9.97 | K74: 0 | L74: 0.72 | M74: 10.69 | N74: Card
A75: 120073 | B75: 201 | C75: 45846.258 | D75: 45846 | E75: Breakfast | F75: Dine-In | G75: Egg Muffin | H75: Cinnamon | I75: 1 | J75: 3.63 | K75: 0 | L75: 0.34 | M75: 4.07 | N75: MobilePay
A76: 120074 | B76: 301 | C76: 45870.353 | D76: 45870 | E76: Breakfast | F76: Takeout | G76: Egg Muffin | I76: 1 | J76: 2.59 | K76: 0.57 | L76: 0.24 | M76: 3.46 | N76: Card
A77: 120075 | B77: 402 | C77: 45777.748 | D77: 45777 | E77: Afternoon | F77: Takeout | G77: Milkshake | I77: 1 | J77: 4.26 | K77: 0 | L77: 0.26 | M77: 4.52 | N77: MobilePay
A78: 120076 | B78: 103 | C78: 45788.353 | D78: 45788 | E78: Breakfast | F78: Delivery | G78: Sausage Biscuit | I78: 1 | J78: 3.06 | K78: 0 | L78: 0.18 | M78: 3.24 | N78: Card
A79: 120077 | B79: 202 | C79: 45769.431 | D79: 45769 | E79: Morning | F79: Takeout | G79: Latte | H79: Almond Milk | I79: 1 | J79: 3.17 | K79: 0 | L79: 0.25 | M79: 4.12 | N79: Card
A80: 120078 | B80: 403 | C80: 45793.356 | D80: 45793 | E80: Breakfast | F80: Dine-In | G80: Milkshake | I80: 1 | J80: 4.02 | K80: 0 | L80: 0.28 | M80: 4.3 | N80: Card
A81: 120079 | B81: 403 | C81: 45835.381 | D81: 45835 | E81: Breakfast | F81: Takeout | G81: Latte | H81: Light Ice | I81: 1 | J81: 2.74 | K81: 0.41 | L81: 0.17 | M81: 2.5 | N81: Card
A82: 120080 | B82: 201 | C82: 45775.624 | D82: 45775 | E82: Lunch | F82: Dine-In | G82: Chicken Sandwich Combo | H82: Gluten-Free Bun | I82: 1 | J82: 8.88 | K82: 0 | L82: 0.84 | M82: 10.72 | N82: Cash
A83: 120081 | B83: 402 | C83: 45808.782 | D83: 45808 | E83: Dinner | F83: Takeout | G83: Double Cheeseburger | I83: 1 | J83: 5.89 | K83: 0 | L83: 0.5 | M83: 6.39 | N83: Card
A84: 120082 | B84: 401 | C84: 45814.302 | D84: 45814 | E84: Breakfast | F84: Drive-Thru | G84: Egg Muffin | H84: Sausage Patty | I84: 1 | J84: 3.61 | K84: 0 | L84: 0.36 | M84: 5.17 | N84: Card
A85: 120083 | B85: 501 | C85: 45868.22 | D85: 45868 | E85: Breakfast | F85: Drive-Thru | G85: Coffee | I85: 1 | J85: 1.79 | K85: 0 | L85: 0.12 | M85: 1.91 | N85: Card
A86: 120084 | B86: 402 | C86: 45876.731 | D86: 45876 | E86: Afternoon | F86: Dine-In | G86: Onion Rings | H86: Small Size | I86: 1 | J86: 2.91 | K86: 0 | L86: 0.17 | M86: 2.78 | N86: Card
A87: 120085 | B87: 403 | C87: 45829.585 | D87: 45829 | E87: Lunch | F87: Takeout | G87: Double Cheeseburger Combo | I87: 1 | J87: 9.74 | K87: 0 | L87: 0.63 | M87: 10.37 | N87: Card
A88: 120086 | B88: 103 | C88: 45791.906 | D88: 45791 | E88: Dinner | F88: Delivery | G88: Cheeseburger | I88: 1 | J88: 4.8 | K88: 0 | L88: 0.29 | M88: 5.09 | N88: MobilePay
A89: 120087 | B89: 403 | C89: 45874.513 | D89: 45874 | E89: Lunch | F89: Drive-Thru | G89: Spicy Chicken Combo | I89: 1 | J89: 9.45 | K89: 0 | L89: 0.8 | M89: 10.25 | N89: Card
A90: 120088 | B90: 402 | C90: 45776.577 | D90: 45776 | E90: Lunch | F90: Drive-Thru | G90: Chicken Sandwich Combo | H90: Add Jalapenos | I90: 1 | J90: 8.73 | K90: 0 | L90: 0.73 | M90: 9.86 | N90: Card
A91: 120089 | B91: 301 | C91: 45785.569 | D91: 45785 | E91: Lunch | F91: Dine-In | G91: Chicken Nuggets (10pc) | I91: 1 | J91: 5.16 | K91: 0 | L91: 0.36 | M91: 5.52 | N91: GiftCard
A92: 120090 | B92: 102 | C92: 45796.475 | D92: 45796 | E92: Morning | F92: Drive-Thru | G92: Coffee | H92: Extra Ice | I92: 1 | J92: 1.91 | K92: 0 | L92: 0.13 | M92: 2.04 | N92: Card
A93: 120091 | B93: 103 | C93: 45829.47 | D93: 45829 | E93: Lunch | F93: Dine-In | G93: Iced Tea | I93: 2 | J93: 2.02 | K93: 0 | L93: 0.26 | M93: 4.3 | N93: Card
A94: 120092 | B94: 301 | C94: 45788.65 | D94: 45788 | E94: Afternoon | F94: Dine-In | G94: Chicken Nuggets (10pc) | I94: 2 | J94: 4.76 | K94: 0 | L94: 0.76 | M94: 10.28 | N94: Card
A95: 120093 | B95: 101 | C95: 45805.562 | D95: 45805 | E95: Lunch | F95: Drive-Thru | G95: Onion Rings | I95: 1 | J95: 3.05 | K95: 0 | L95: 0.27 | M95: 3.32 | N95: Card
A96: 120094 | B96: 102 | C96: 45791.548 | D96: 45791 | E96: Lunch | F96: Drive-Thru | G96: Chicken Sandwich Combo | H96: No Onions | I96: 1 | J96: 8.79 | K96: 0 | L96: 0.53 | M96: 9.32 | N96: Card
A97: 120095 | B97: 201 | C97: 45758.579 | D97: 45758 | E97: Lunch | F97: Dine-In | G97: Chicken Sandwich Combo | I97: 1 | J97: 8.26 | K97: 0 | L97: 0.78 | M97: 9.04 | N97: Cash
A98: 120096 | B98: 501 | C98: 45760.495 | D98: 45760 | E98: Lunch | F98: Dine-In | G98: Chicken Sandwich Combo | H98: Add Bacon | I98: 1 | J98: 9.14 | K98: 0 | L98: 0.61 | M98: 10.75 | N98: Card
A99: 120097 | B99: 401 | C99: 45869.466 | D99: 45869 | E99: Lunch | F99: Takeout | G99: Spicy Chicken Sandwich | I99: 2 | J99: 5.74 | K99: 0 | L99: 0.92 | M99: 12.4 | N99: Card
A100: 120098 | B100: 402 | C100: 45821.256 | D100: 45821 | E100: Breakfast | F100: Dine-In | G100: Latte | H100: Light Ice | I100: 1 | J100: 3.24 | K100: 0 | L100: 0.26 | M100: 3.5 | N100: MobilePay
...

Sheet Cleaning
A1: Order_ID | B1: Store_ID | C1: Transaction_Date | D1: Time | E1: Business_Day | F1: Day_Of_Week | G1: Day_Part | H1: Service_Mode_ | I1: Service_Mode | J1: Menu_Item | K1: Modifier_ | L1: Modifier | M1: Quantity | N1: Unit Price | O1: Unit_Price | P1: Gross | Q1: Discount_ | R1: Discount | S1: Tax_ | T1: Tax | U1: Total Amount | V1: Total_Amount | W1: Payment Type | X1: Payment_type
A2: 120000 | B2: 102 | C2: 45843 | D2: 0.25981481 | E2: 45843 | F2: =TEXT(Table1[[#This Row],[Business_Day]],"dddd") -> Saturday | G2: Breakfast | H2: Drive-Thru | I2: =IF(H2="","Unknown",H2) -> Drive-Thru | J2: Bottled Water | L2: =IF(K2="","No Modifier",K2) -> No Modifier | M2: 1 | N2: 1.48 | O2: =(V2-T2+R2)/M2 -> 1.48 | P2: =PRODUCT(M2,O2) -> 1.48 | Q2: 0.15 | R2: =IF(ISBLANK(Q2),ROUND((M2*O2)+T2-V2,2),Q2) -> 0.15 | S2: 0.1 | T2: =IF(S2="",V2-P2+R2,S2) -> 0.1 | U2: 1.43 | V2: =IF(U2="",(M2*O2)-R2+T2,U2) -> 1.43 | W2: Cash | X2: =IF(W2="","Card",W2) -> Cash
A3: 120001 | B3: 201 | C3: 45843 | D3: 0.49225694 | E3: 45843 | F3: =TEXT(Table1[[#This Row],[Business_Day]],"dddd") -> Saturday | G3: Lunch | H3: Dine-In | I3: =IF(H3="","Unknown",H3) -> Dine-In | J3: Chicken Sandwich | L3: =IF(K3="","No Modifier",K3) -> No Modifier | M3: 1 | N3: 5.34 | O3: =(V3-T3+R3)/M3 -> 5.34 | P3: =PRODUCT(M3,O3) -> 5.34 | Q3: 0 | R3: =IF(ISBLANK(Q3),ROUND((M3*O3)+T3-V3,2),Q3) -> 0 | S3: 0.45 | T3: =IF(S3="",V3-P3+R3,S3) -> 0.45 | U3: 5.79 | V3: =IF(U3="",(M3*O3)-R3+T3,U3) -> 5.79 | W3: Card | X3: =IF(W3="","Card",W3) -> Card
A4: 120002 | B4: 403 | C4: 45760 | D4: 0.33721065 | E4: 45760 | F4: =TEXT(Table1[[#This Row],[Business_Day]],"dddd") -> Sunday | G4: Breakfast | H4: Takeout | I4: =IF(H4="","Unknown",H4) -> Takeout | J4: Bottled Water | K4: Light Ice | L4: =IF(K4="","No Modifier",K4) -> Light Ice | M4: 1 | N4: 1.49 | O4: =(V4-T4+R4)/M4 -> 1.49 | P4: =PRODUCT(M4,O4) -> 1.49 | Q4: 0.15 | R4: =IF(ISBLANK(Q4),ROUND((M4*O4)+T4-V4,2),Q4) -> 0.15 | S4: 0.1 | T4: =IF(S4="",V4-P4+R4,S4) -> 0.1 | U4: 1.44 | V4: =IF(U4="",(M4*O4)-R4+T4,U4) -> 1.44 | W4: Cash | X4: =IF(W4="","Card",W4) -> Cash | Z4: Row Labels | AA4: Sum of Total_Amount
A5: 120003 | B5: 301 | C5: 45833 | D5: 0.27936343 | E5: 45833 | F5: =TEXT(Table1[[#This Row],[Business_Day]],"dddd") -> Wednesday | G5: Breakfast | H5: Drive-Thru | I5: =IF(H5="","Unknown",H5) -> Drive-Thru | J5: Egg Muffin | K5: No Cheese | L5: =IF(K5="","No Modifier",K5) -> No Cheese | M5: 1 | N5: 3.62 | O5: =(V5-T5+R5)/M5 -> 3.62 | P5: =PRODUCT(M5,O5) -> 3.62 | Q5: 0 | R5: =IF(ISBLANK(Q5),ROUND((M5*O5)+T5-V5,2),Q5) -> 0 | S5: 0.34 | T5: =IF(S5="",V5-P5+R5,S5) -> 0.34 | U5: 3.96 | V5: =IF(U5="",(M5*O5)-R5+T5,U5) -> 3.96 | W5: Cash | X5: =IF(W5="","Card",W5) -> Cash | Z5: Card | AA5: 6648.29
A6: 120004 | B6: 301 | C6: 45870 | D6: 0.54069444 | E6: 45870 | F6: =TEXT(Table1[[#This Row],[Business_Day]],"dddd") -> Friday | G6: Lunch | H6: Drive-Thru | I6: =IF(H6="","Unknown",H6) -> Drive-Thru | J6: Spicy Chicken Combo | L6: =IF(K6="","No Modifier",K6) -> No Modifier | M6: 2 | N6: 9.17 | O6: =(V6-T6+R6)/M6 -> 9.17 | P6: =PRODUCT(M6,O6) -> 18.34 | Q6: 0 | R6: =IF(ISBLANK(Q6),ROUND((M6*O6)+T6-V6,2),Q6) -> 0 | S6: 1.38 | T6: =IF(S6="",V6-P6+R6,S6) -> 1.38 | U6: 19.72 | V6: =IF(U6="",(M6*O6)-R6+T6,U6) -> 19.72 | W6: Card | X6: =IF(W6="","Card",W6) -> Card | Z6: Cash | AA6: 2339.22
A7: 120005 | B7: 501 | C7: 45850 | D7: 0.52258102 | E7: 45850 | F7: =TEXT(Table1[[#This Row],[Business_Day]],"dddd") -> Saturday | G7: Lunch | H7: Dine-In | I7: =IF(H7="","Unknown",H7) -> Dine-In | J7: Double Cheeseburger | L7: =IF(K7="","No Modifier",K7) -> No Modifier | M7: 1 | N7: 5.64 | O7: =(V7-T7+R7)/M7 -> 5.64 | P7: =PRODUCT(M7,O7) -> 5.64 | Q7: 0 | R7: =IF(ISBLANK(Q7),ROUND((M7*O7)+T7-V7,2),Q7) -> 0 | S7: 0.37 | T7: =IF(S7="",V7-P7+R7,S7) -> 0.37 | U7: 6.01 | V7: =IF(U7="",(M7*O7)-R7+T7,U7) -> 6.01 | W7: Card | X7: =IF(W7="","Card",W7) -> Card | Z7: GiftCard | AA7: 645.21
A8: 120006 | B8: 101 | C8: 45864 | D8: 0.24761574 | E8: 45864 | F8: =TEXT(Table1[[#This Row],[Business_Day]],"dddd") -> Saturday | G8: Afternoon | H8: Delivery | I8: =IF(H8="","Unknown",H8) -> Delivery | J8: Onion Rings | L8: =IF(K8="","No Modifier",K8) -> No Modifier | M8: 1 | N8: 3.59 | O8: =(V8-T8+R8)/M8 -> 3.59 | P8: =PRODUCT(M8,O8) -> 3.59 | Q8: 0.54 | R8: =IF(ISBLANK(Q8),ROUND((M8*O8)+T8-V8,2),Q8) -> 0.54 | S8: 0.29 | T8: =IF(S8="",V8-P8+R8,S8) -> 0.29 | U8: 3.34 | V8: =IF(U8="",(M8*O8)-R8+T8,U8) -> 3.34 | W8: MobilePay | X8: =IF(W8="","Card",W8) -> MobilePay | Z8: MobilePay | AA8: 1698.02
A9: 120007 | B9: 403 | C9: 45859 | D9: 0.20011574 | E9: 45859 | F9: =TEXT(Table1[[#This Row],[Business_Day]],"dddd") -> Monday | G9: Afternoon | H9: Takeout | I9: =IF(H9="","Unknown",H9) -> Takeout | J9: Soft Drink (Medium) | L9: =IF(K9="","No Modifier",K9) -> No Modifier | M9: 1 | N9: 1.8 | O9: =(V9-T9+R9)/M9 -> 1.8 | P9: =PRODUCT(M9,O9) -> 1.8 | Q9: 0.27 | R9: =IF(ISBLANK(Q9),ROUND((M9*O9)+T9-V9,2),Q9) -> 0.27 | S9: 0.11 | T9: =IF(S9="",V9-P9+R9,S9) -> 0.11 | U9: 1.64 | V9: =IF(U9="",(M9*O9)-R9+T9,U9) -> 1.64 | W9: Cash | X9: =IF(W9="","Card",W9) -> Cash | Z9: (blank) | AA9: 310.9
A10: 120008 | B10: 102 | C10: 45810 | D10: 0.464375 | E10: 45810 | F10: =TEXT(Table1[[#This Row],[Business_Day]],"dddd") -> Monday | G10: Late Night | H10: Delivery | I10: =IF(H10="","Unknown",H10) -> Delivery | J10: Chicken Sandwich | K10: Extra Sauce | L10: =IF(K10="","No Modifier",K10) -> Extra Sauce | M10: 2 | N10: 5.22 | O10: =(V10-T10+R10)/M10 -> 5.47 | P10: =PRODUCT(M10,O10) -> 10.94 | Q10: 0 | R10: =IF(ISBLANK(Q10),ROUND((M10*O10)+T10-V10,2),Q10) -> 0 | S10: 0.79 | T10: =IF(S10="",V10-P10+R10,S10) -> 0.79 | U10: 11.73 | V10: =IF(U10="",(M10*O10)-R10+T10,U10) -> 11.73 | W10: Card | X10: =IF(W10="","Card",W10) -> Card | Z10: Grand Total | AA10: 11641.64
A11: 120009 | B11: 402 | C11: 45850 | D11: 0.22292824 | E11: 45850 | F11: =TEXT(Table1[[#This Row],[Business_Day]],"dddd") -> Saturday | G11: Breakfast | H11: Drive-Thru | I11: =IF(H11="","Unknown",H11) -> Drive-Thru | J11: Hash Browns | L11: =IF(K11="","No Modifier",K11) -> No Modifier | M11: 1 | N11: 2 | O11: =(V11-T11+R11)/M11 -> 2 | P11: =PRODUCT(M11,O11) -> 2 | Q11: 0 | R11: =IF(ISBLANK(Q11),ROUND((M11*O11)+T11-V11,2),Q11) -> 0 | S11: 0.12 | T11: =IF(S11="",V11-P11+R11,S11) -> 0.12 | U11: 2.12 | V11: =IF(U11="",(M11*O11)-R11+T11,U11) -> 2.12 | W11: Card | X11: =IF(W11="","Card",W11) -> Card
A12: 120010 | B12: 103 | C12: 45766 | D12: 0.38599537 | E12: 45766 | F12: =TEXT(Table1[[#This Row],[Business_Day]],"dddd") -> Saturday | G12: Dinner | H12: Takeout | I12: =IF(H12="","Unknown",H12) -> Takeout | J12: Double Cheeseburger | L12: =IF(K12="","No Modifier",K12) -> No Modifier | M12: 1 | N12: 5.55 | O12: =(V12-T12+R12)/M12 -> 5.55 | P12: =PRODUCT(M12,O12) -> 5.55 | Q12: 0 | R12: =IF(ISBLANK(Q12),ROUND((M12*O12)+T12-V12,2),Q12) -> 0 | S12: 0.33 | T12: =IF(S12="",V12-P12+R12,S12) -> 0.33 | U12: 5.88 | V12: =IF(U12="",(M12*O12)-R12+T12,U12) -> 5.88 | W12: Card | X12: =IF(W12="","Card",W12) -> Card
A13: 120011 | B13: 102 | C13: 45854 | D13: 0.46420139 | E13: 45854 | F13: =TEXT(Table1[[#This Row],[Business_Day]],"dddd") -> Wednesday | G13: Morning | H13: Dine-In | I13: =IF(H13="","Unknown",H13) -> Dine-In | J13: Apple Pie | L13: =IF(K13="","No Modifier",K13) -> No Modifier | M13: 1 | N13: 1.53 | O13: =(V13-T13+R13)/M13 -> 1.53 | P13: =PRODUCT(M13,O13) -> 1.53 | Q13: 0 | R13: =IF(ISBLANK(Q13),ROUND((M13*O13)+T13-V13,2),Q13) -> 0 | S13: 0.1 | T13: =IF(S13="",V13-P13+R13,S13) -> 0.1 | U13: 1.63 | V13: =IF(U13="",(M13*O13)-R13+T13,U13) -> 1.63 | W13: Card | X13: =IF(W13="","Card",W13) -> Card
A14: 120012 | B14: 201 | C14: 45816 | D14: 0.34299769 | E14: 45816 | F14: =TEXT(Table1[[#This Row],[Business_Day]],"dddd") -> Sunday | G14: Breakfast | H14: Takeout | I14: =IF(H14="","Unknown",H14) -> Takeout | J14: Sausage Biscuit | K14: Sausage Patty | L14: =IF(K14="","No Modifier",K14) -> Sausage Patty | M14: 2 | N14: 3.1 | O14: =(V14-T14+R14)/M14 -> 4.3 | P14: =PRODUCT(M14,O14) -> 8.6 | Q14: 0 | R14: =IF(ISBLANK(Q14),ROUND((M14*O14)+T14-V14,2),Q14) -> 0 | S14: 0.64 | T14: =IF(S14="",V14-P14+R14,S14) -> 0.64 | U14: 9.24 | V14: =IF(U14="",(M14*O14)-R14+T14,U14) -> 9.24 | W14: Card | X14: =IF(W14="","Card",W14) -> Card
A15: 120013 | B15: 103 | C15: 45851 | D15: 0.44290509 | E15: 45851 | F15: =TEXT(Table1[[#This Row],[Business_Day]],"dddd") -> Sunday | G15: Morning | H15: Takeout | I15: =IF(H15="","Unknown",H15) -> Takeout | J15: Coffee | K15: Oat Milk | L15: =IF(K15="","No Modifier",K15) -> Oat Milk | M15: 2 | N15: 1.51 | O15: =(V15-T15+R15)/M15 -> 2.21 | P15: =PRODUCT(M15,O15) -> 4.42 | Q15: 0 | R15: =IF(ISBLANK(Q15),ROUND((M15*O15)+T15-V15,2),Q15) -> 0 | S15: 0.27 | T15: =IF(S15="",V15-P15+R15,S15) -> 0.27 | U15: 4.69 | V15: =IF(U15="",(M15*O15)-R15+T15,U15) -> 4.69 | W15: Cash | X15: =IF(W15="","Card",W15) -> Cash
A16: 120014 | B16: 201 | C16: 45758 | D16: 0.52613426 | E16: 45758 | F16: =TEXT(Table1[[#This Row],[Business_Day]],"dddd") -> Friday | G16: Lunch | H16: Dine-In | I16: =IF(H16="","Unknown",H16) -> Dine-In | J16: Spicy Chicken Combo | L16: =IF(K16="","No Modifier",K16) -> No Modifier | M16: 1 | N16: 8.43 | O16: =(V16-T16+R16)/M16 -> 8.43 | P16: =PRODUCT(M16,O16) -> 8.43 | Q16: 0 | R16: =IF(ISBLANK(Q16),ROUND((M16*O16)+T16-V16,2),Q16) -> 0 | S16: 0.67 | T16: =IF(S16="",V16-P16+R16,S16) -> 0.67 | U16: 9.1 | V16: =IF(U16="",(M16*O16)-R16+T16,U16) -> 9.1 | W16: Card | X16: =IF(W16="","Card",W16) -> Card
A17: 120015 | B17: 102 | C17: 45799 | D17: 0.37921296 | E17: 45799 | F17: =TEXT(Table1[[#This Row],[Business_Day]],"dddd") -> Thursday | G17: Breakfast | H17: Delivery | I17: =IF(H17="","Unknown",H17) -> Delivery | J17: Egg Muffin | L17: =IF(K17="","No Modifier",K17) -> No Modifier | M17: 1 | N17: 3.1 | O17: =(V17-T17+R17)/M17 -> 3.1 | P17: =PRODUCT(M17,O17) -> 3.1 | Q17: 0 | R17: =IF(ISBLANK(Q17),ROUND((M17*O17)+T17-V17,2),Q17) -> 0 | S17: 0.23 | T17: =IF(S17="",V17-P17+R17,S17) -> 0.23 | U17: 3.33 | V17: =IF(U17="",(M17*O17)-R17+T17,U17) -> 3.33 | W17: Card | X17: =IF(W17="","Card",W17) -> Card
A18: 120016 | B18: 403 | C18: 45774 | D18: 0.38887731 | E18: 45774 | F18: =TEXT(Table1[[#This Row],[Business_Day]],"dddd") -> Sunday | G18: Breakfast | H18: Drive-Thru | I18: =IF(H18="","Unknown",H18) -> Drive-Thru | J18: Egg Muffin | L18: =IF(K18="","No Modifier",K18) -> No Modifier | M18: 1 | N18: 2.99 | O18: =(V18-T18+R18)/M18 -> 2.99 | P18: =PRODUCT(M18,O18) -> 2.99 | Q18: 0 | R18: =IF(ISBLANK(Q18),ROUND((M18*O18)+T18-V18,2),Q18) -> 0 | S18: 0.22 | T18: =IF(S18="",V18-P18+R18,S18) -> 0.22 | U18: 3.21 | V18: =IF(U18="",(M18*O18)-R18+T18,U18) -> 3.21 | W18: MobilePay | X18: =IF(W18="","Card",W18) -> MobilePay
A19: 120017 | B19: 403 | C19: 45763 | D19: 0.46226852 | E19: 45763 | F19: =TEXT(Table1[[#This Row],[Business_Day]],"dddd") -> Wednesday | G19: Lunch | H19: Takeout | I19: =IF(H19="","Unknown",H19) -> Takeout | J19: Cheeseburger | L19: =IF(K19="","No Modifier",K19) -> No Modifier | M19: 1 | N19: 4.59 | O19: =(V19-T19+R19)/M19 -> 5 | P19: =PRODUCT(M19,O19) -> 5 | Q19: 0 | R19: =IF(ISBLANK(Q19),ROUND((M19*O19)+T19-V19,2),Q19) -> 0 | T19: =IF(S19="",V19-P19+R19,S19) -> 0 | U19: 5 | V19: =IF(U19="",(M19*O19)-R19+T19,U19) -> 5 | W19: Card | X19: =IF(W19="","Card",W19) -> Card
A20: 120018 | B20: 403 | C20: 45831 | D20: 0.39940972 | E20: 45831 | F20: =TEXT(Table1[[#This Row],[Business_Day]],"dddd") -> Monday | G20: Breakfast | H20: Takeout | I20: =IF(H20="","Unknown",H20) -> Takeout | J20: Sausage Biscuit | K20: Extra Egg | L20: =IF(K20="","No Modifier",K20) -> Extra Egg | M20: 2 | N20: 2.81 | O20: =(V20-T20+R20)/M20 -> 3.81 | P20: =PRODUCT(M20,O20) -> 7.62 | Q20: 0 | R20: =IF(ISBLANK(Q20),ROUND((M20*O20)+T20-V20,2),Q20) -> 0 | S20: 0.55 | T20: =IF(S20="",V20-P20+R20,S20) -> 0.55 | U20: 8.17 | V20: =IF(U20="",(M20*O20)-R20+T20,U20) -> 8.17 | W20: Card | X20: =IF(W20="","Card",W20) -> Card
A21: 120019 | B21: 103 | C21: 45848 | D21: 0.32767361 | E21: 45848 | F21: =TEXT(Table1[[#This Row],[Business_Day]],"dddd") -> Thursday | G21: Dinner | H21: Dine-In | I21: =IF(H21="","Unknown",H21) -> Dine-In | J21: Chicken Sandwich | K21: Extra Sauce | L21: =IF(K21="","No Modifier",K21) -> Extra Sauce | M21: 1 | N21: 4.87 | O21: =(V21-T21+R21)/M21 -> 5.12 | P21: =PRODUCT(M21,O21) -> 5.12 | Q21: 0 | R21: =IF(ISBLANK(Q21),ROUND((M21*O21)+T21-V21,2),Q21) -> 0 | S21: 0.37 | T21: =IF(S21="",V21-P21+R21,S21) -> 0.37 | U21: 5.49 | V21: =IF(U21="",(M21*O21)-R21+T21,U21) -> 5.49 | W21: Card | X21: =IF(W21="","Card",W21) -> Card
A22: 120020 | B22: 201 | C22: 45761 | D22: 0.47383102 | E22: 45761 | F22: =TEXT(Table1[[#This Row],[Business_Day]],"dddd") -> Monday | G22: Morning | H22: Drive-Thru | I22: =IF(H22="","Unknown",H22) -> Drive-Thru | J22: Coffee | K22: Sugar-Free Syrup | L22: =IF(K22="","No Modifier",K22) -> Sugar-Free Syrup | M22: 1 | N22: 2.18 | O22: =(V22-T22+R22)/M22 -> 2.48 | P22: =PRODUCT(M22,O22) -> 2.48 | Q22: 0 | R22: =IF(ISBLANK(Q22),ROUND((M22*O22)+T22-V22,2),Q22) -> 0 | S22: 0.19 | T22: =IF(S22="",V22-P22+R22,S22) -> 0.19 | U22: 2.67 | V22: =IF(U22="",(M22*O22)-R22+T22,U22) -> 2.67 | W22: MobilePay | X22: =IF(W22="","Card",W22) -> MobilePay
A23: 120021 | B23: 101 | C23: 45845 | D23: 0.27587963 | E23: 45845 | F23: =TEXT(Table1[[#This Row],[Business_Day]],"dddd") -> Monday | G23: Breakfast | H23: Dine-In | I23: =IF(H23="","Unknown",H23) -> Dine-In | J23: Sausage Biscuit | K23: Cinnamon | L23: =IF(K23="","No Modifier",K23) -> Cinnamon | M23: 1 | N23: 2.98 | O23: =(V23-T23+R23)/M23 -> 3.08 | P23: =PRODUCT(M23,O23) -> 3.08 | Q23: 0 | R23: =IF(ISBLANK(Q23),ROUND((M23*O23)+T23-V23,2),Q23) -> 0 | S23: 0.26 | T23: =IF(S23="",V23-P23+R23,S23) -> 0.26 | U23: 3.34 | V23: =IF(U23="",(M23*O23)-R23+T23,U23) -> 3.34 | W23: Cash | X23: =IF(W23="","Card",W23) -> Cash
A24: 120022 | B24: 403 | C24: 45758 | D24: 0.24145833 | E24: 45758 | F24: =TEXT(Table1[[#This Row],[Business_Day]],"dddd") -> Friday | G24: Afternoon | H24: Dine-In | I24: =IF(H24="","Unknown",H24) -> Dine-In | J24: Ice Cream Cone | K24: Cinnamon | L24: =IF(K24="","No Modifier",K24) -> Cinnamon | M24: 1 | N24: 1.65 | O24: =(V24-T24+R24)/M24 -> 1.75 | P24: =PRODUCT(M24,O24) -> 1.75 | Q24: 0 | R24: =IF(ISBLANK(Q24),ROUND((M24*O24)+T24-V24,2),Q24) -> 0 | S24: 0.13 | T24: =IF(S24="",V24-P24+R24,S24) -> 0.13 | U24: 1.88 | V24: =IF(U24="",(M24*O24)-R24+T24,U24) -> 1.88 | W24: Card | X24: =IF(W24="","Card",W24) -> Card
A25: 120023 | B25: 201 | C25: 45758 | D25: 0.11373843 | E25: 45758 | F25: =TEXT(Table1[[#This Row],[Business_Day]],"dddd") -> Friday | G25: Lunch | H25: Drive-Thru | I25: =IF(H25="","Unknown",H25) -> Drive-Thru | J25: Spicy Chicken Sandwich | K25: No Pickles | L25: =IF(K25="","No Modifier",K25) -> No Pickles | M25: 1 | N25: 5.09 | O25: =(V25-T25+R25)/M25 -> 5.09 | P25: =PRODUCT(M25,O25) -> 5.09 | Q25: 0 | R25: =IF(ISBLANK(Q25),ROUND((M25*O25)+T25-V25,2),Q25) -> 0 | S25: 0.41 | T25: =IF(S25="",V25-P25+R25,S25) -> 0.41 | U25: 5.5 | V25: =IF(U25="",(M25*O25)-R25+T25,U25) -> 5.5 | W25: Cash | X25: =IF(W25="","Card",W25) -> Cash
A26: 120024 | B26: 103 | C26: 45842 | D26: 0.23796296 | E26: 45842 | F26: =TEXT(Table1[[#This Row],[Business_Day]],"dddd") -> Friday | G26: Afternoon | H26: Takeout | I26: =IF(H26="","Unknown",H26) -> Takeout | J26: Ice Cream Cone | L26: =IF(K26="","No Modifier",K26) -> No Modifier | M26: 1 | N26: 1.58 | O26: =(V26-T26+R26)/M26 -> 1.58 | P26: =PRODUCT(M26,O26) -> 1.58 | Q26: 0 | R26: =IF(ISBLANK(Q26),ROUND((M26*O26)+T26-V26,2),Q26) -> 0 | S26: 0.11 | T26: =IF(S26="",V26-P26+R26,S26) -> 0.11 | U26: 1.69 | V26: =IF(U26="",(M26*O26)-R26+T26,U26) -> 1.69 | W26: Card | X26: =IF(W26="","Card",W26) -> Card
A27: 120025 | B27: 401 | C27: 45805 | D27: 0.32342593 | E27: 45805 | F27: =TEXT(Table1[[#This Row],[Business_Day]],"dddd") -> Wednesday | G27: Dinner | H27: Takeout | I27: =IF(H27="","Unknown",H27) -> Takeout | J27: Chicken Sandwich | K27: Extra Cheese | L27: =IF(K27="","No Modifier",K27) -> Extra Cheese | M27: 1 | N27: 5.43 | O27: =(V27-T27+R27)/M27 -> 5.93 | P27: =PRODUCT(M27,O27) -> 5.93 | Q27: 0 | R27: =IF(ISBLANK(Q27),ROUND((M27*O27)+T27-V27,2),Q27) -> 0 | S27: 0.56 | T27: =IF(S27="",V27-P27+R27,S27) -> 0.56 | U27: 6.49 | V27: =IF(U27="",(M27*O27)-R27+T27,U27) -> 6.49 | W27: Card | X27: =IF(W27="","Card",W27) -> Card
A28: 120026 | B28: 402 | C28: 45807 | D28: 0.22277778 | E28: 45807 | F28: =TEXT(Table1[[#This Row],[Business_Day]],"dddd") -> Friday | G28: Afternoon | H28: Drive-Thru | I28: =IF(H28="","Unknown",H28) -> Drive-Thru | J28: Milkshake | K28: Cinnamon | L28: =IF(K28="","No Modifier",K28) -> Cinnamon | M28: 1 | N28: 3.61 | O28: =(V28-T28+R28)/M28 -> 3.71 | P28: =PRODUCT(M28,O28) -> 3.71 | Q28: 0 | R28: =IF(ISBLANK(Q28),ROUND((M28*O28)+T28-V28,2),Q28) -> 0 | S28: 0.33 | T28: =IF(S28="",V28-P28+R28,S28) -> 0.33 | U28: 4.04 | V28: =IF(U28="",(M28*O28)-R28+T28,U28) -> 4.04 | W28: Cash | X28: =IF(W28="","Card",W28) -> Cash
A29: 120027 | B29: 402 | C29: 45843 | D29: 0.16996528 | E29: 45843 | F29: =TEXT(Table1[[#This Row],[Business_Day]],"dddd") -> Saturday | G29: Afternoon | H29: Dine-In | I29: =IF(H29="","Unknown",H29) -> Dine-In | J29: French Fries | K29: Small Size | L29: =IF(K29="","No Modifier",K29) -> Small Size | M29: 1 | N29: 2.75 | O29: =(V29-T29+R29)/M29 -> 2.45 | P29: =PRODUCT(M29,O29) -> 2.45 | Q29: 0 | R29: =IF(ISBLANK(Q29),ROUND((M29*O29)+T29-V29,2),Q29) -> 0 | S29: 0.17 | T29: =IF(S29="",V29-P29+R29,S29) -> 0.17 | U29: 2.62 | V29: =IF(U29="",(M29*O29)-R29+T29,U29) -> 2.62 | W29: Card | X29: =IF(W29="","Card",W29) -> Card
A30: 120028 | B30: 201 | C30: 45829 | D30: 0.28814815 | E30: 45829 | F30: =TEXT(Table1[[#This Row],[Business_Day]],"dddd") -> Saturday | G30: Dinner | H30: Drive-Thru | I30: =IF(H30="","Unknown",H30) -> Drive-Thru | J30: Cheeseburger | L30: =IF(K30="","No Modifier",K30) -> No Modifier | M30: 1 | N30: 4.29 | O30: =(V30-T30+R30)/M30 -> 4.29 | P30: =PRODUCT(M30,O30) -> 4.29 | Q30: 0 | R30: =IF(ISBLANK(Q30),ROUND((M30*O30)+T30-V30,2),Q30) -> 0 | S30: 0.36 | T30: =IF(S30="",V30-P30+R30,S30) -> 0.36 | U30: 4.65 | V30: =IF(U30="",(M30*O30)-R30+T30,U30) -> 4.65 | W30: Card | X30: =IF(W30="","Card",W30) -> Card
A31: 120029 | B31: 202 | C31: 45875 | D31: 0.098402778 | E31: 45875 | F31: =TEXT(Table1[[#This Row],[Business_Day]],"dddd") -> Wednesday | G31: Lunch | H31: Delivery | I31: =IF(H31="","Unknown",H31) -> Delivery | J31: Chicken Sandwich | K31: No Onions | L31: =IF(K31="","No Modifier",K31) -> No Onions | M31: 3 | N31: 5.28 | O31: =(V31-T31+R31)/M31 -> 5.28 | P31: =PRODUCT(M31,O31) -> 15.84 | Q31: 0 | R31: =IF(ISBLANK(Q31),ROUND((M31*O31)+T31-V31,2),Q31) -> 0 | S31: 1.35 | T31: =IF(S31="",V31-P31+R31,S31) -> 1.35 | U31: 17.19 | V31: =IF(U31="",(M31*O31)-R31+T31,U31) -> 17.19 | W31: Card | X31: =IF(W31="","Card",W31) -> Card
A32: 120030 | B32: 103 | C32: 45830 | D32: 0.30103009 | E32: 45830 | F32: =TEXT(Table1[[#This Row],[Business_Day]],"dddd") -> Sunday | G32: Breakfast | H32: Takeout | I32: =IF(H32="","Unknown",H32) -> Takeout | J32: Sausage Biscuit | L32: =IF(K32="","No Modifier",K32) -> No Modifier | M32: 1 | N32: 2.89 | O32: =(V32-T32+R32)/M32 -> 2.99 | P32: =PRODUCT(M32,O32) -> 2.99 | Q32: 0.15 | R32: =IF(ISBLANK(Q32),ROUND((M32*O32)+T32-V32,2),Q32) -> 0.15 | S32: 0.27 | T32: =IF(S32="",V32-P32+R32,S32) -> 0.27 | U32: 3.11 | V32: =IF(U32="",(M32*O32)-R32+T32,U32) -> 3.11 | W32: Cash | X32: =IF(W32="","Card",W32) -> Cash
A33: 120031 | B33: 101 | C33: 45847 | D33: 0.3284838 | E33: 45847 | F33: =TEXT(Table1[[#This Row],[Business_Day]],"dddd") -> Wednesday | G33: Dinner | H33: Delivery | I33: =IF(H33="","Unknown",H33) -> Delivery | J33: Cheeseburger Combo | L33: =IF(K33="","No Modifier",K33) -> No Modifier | M33: 2 | N33: 9.42 | O33: =(V33-T33+R33)/M33 -> 9.42 | P33: =PRODUCT(M33,O33) -> 18.84 | Q33: 0 | R33: =IF(ISBLANK(Q33),ROUND((M33*O33)+T33-V33,2),Q33) -> 0 | S33: 1.41 | T33: =IF(S33="",V33-P33+R33,S33) -> 1.41 | U33: 20.25 | V33: =IF(U33="",(M33*O33)-R33+T33,U33) -> 20.25 | W33: Card | X33: =IF(W33="","Card",W33) -> Card
A34: 120032 | B34: 103 | C34: 45865 | D34: 0.4578588 | E34: 45865 | F34: =TEXT(Table1[[#This Row],[Business_Day]],"dddd") -> Sunday | G34: Late Night | H34: Drive-Thru | I34: =IF(H34="","Unknown",H34) -> Drive-Thru | J34: Spicy Chicken Sandwich | L34: =IF(K34="","No Modifier",K34) -> No Modifier | M34: 1 | N34: 5.63 | O34: =(V34-T34+R34)/M34 -> 6.63 | P34: =PRODUCT(M34,O34) -> 6.63 | Q34: 0 | R34: =IF(ISBLANK(Q34),ROUND((M34*O34)+T34-V34,2),Q34) -> 0 | S34: 0.48 | T34: =IF(S34="",V34-P34+R34,S34) -> 0.48 | U34: 7.11 | V34: =IF(U34="",(M34*O34)-R34+T34,U34) -> 7.11 | W34: MobilePay | X34: =IF(W34="","Card",W34) -> MobilePay
A35: 120033 | B35: 501 | C35: 45834 | D35: 0.40443287 | E35: 45834 | F35: =TEXT(Table1[[#This Row],[Business_Day]],"dddd") -> Thursday | G35: Dinner | H35: Dine-In | I35: =IF(H35="","Unknown",H35) -> Dine-In | J35: Cheeseburger | L35: =IF(K35="","No Modifier",K35) -> No Modifier | M35: 1 | N35: 4.14 | O35: =(V35-T35+R35)/M35 -> 4.14 | P35: =PRODUCT(M35,O35) -> 4.14 | Q35: 0 | R35: =IF(ISBLANK(Q35),ROUND((M35*O35)+T35-V35,2),Q35) -> 0 | S35: 0.33 | T35: =IF(S35="",V35-P35+R35,S35) -> 0.33 | U35: 4.47 | V35: =IF(U35="",(M35*O35)-R35+T35,U35) -> 4.47 | W35: Cash | X35: =IF(W35="","Card",W35) -> Cash
A36: 120034 | B36: 202 | C36: 45761 | D36: 0.24270833 | E36: 45761 | F36: =TEXT(Table1[[#This Row],[Business_Day]],"dddd") -> Monday | G36: Afternoon | H36: Takeout | I36: =IF(H36="","Unknown",H36) -> Takeout | J36: Iced Tea | L36: =IF(K36="","No Modifier",K36) -> No Modifier | M36: 1 | N36: 2 | O36: =(V36-T36+R36)/M36 -> 2 | P36: =PRODUCT(M36,O36) -> 2 | Q36: 0 | R36: =IF(ISBLANK(Q36),ROUND((M36*O36)+T36-V36,2),Q36) -> 0 | S36: 0.15 | T36: =IF(S36="",V36-P36+R36,S36) -> 0.15 | U36: 2.15 | V36: =IF(U36="",(M36*O36)-R36+T36,U36) -> 2.15 | W36: MobilePay | X36: =IF(W36="","Card",W36) -> MobilePay
A37: 120035 | B37: 101 | C37: 45837 | D37: 0.52167824 | E37: 45837 | F37: =TEXT(Table1[[#This Row],[Business_Day]],"dddd") -> Sunday | G37: Lunch | H37: Takeout | I37: =IF(H37="","Unknown",H37) -> Takeout | J37: Chicken Sandwich | L37: =IF(K37="","No Modifier",K37) -> No Modifier | M37: 1 | N37: 4.94 | O37: =(V37-T37+R37)/M37 -> 5.94 | P37: =PRODUCT(M37,O37) -> 5.94 | Q37: 0 | R37: =IF(ISBLANK(Q37),ROUND((M37*O37)+T37-V37,2),Q37) -> 0 | S37: 0.43 | T37: =IF(S37="",V37-P37+R37,S37) -> 0.43 | U37: 6.37 | V37: =IF(U37="",(M37*O37)-R37+T37,U37) -> 6.37 | W37: Card | X37: =IF(W37="","Card",W37) -> Card
A38: 120036 | B38: 402 | C38: 45876 | D38: 0.47099537 | E38: 45876 | F38: =TEXT(Table1[[#This Row],[Business_Day]],"dddd") -> Thursday | G38: Lunch | H38: Takeout | I38: =IF(H38="","Unknown",H38) -> Takeout | J38: Spicy Chicken Combo | L38: =IF(K38="","No Modifier",K38) -> No Modifier | M38: 1 | N38: 9.39 | O38: =(V38-T38+R38)/M38 -> 9.39 | P38: =PRODUCT(M38,O38) -> 9.39 | Q38: 0 | R38: =IF(ISBLANK(Q38),ROUND((M38*O38)+T38-V38,2),Q38) -> 0 | S38: 0.89 | T38: =IF(S38="",V38-P38+R38,S38) -> 0.89 | U38: 10.28 | V38: =IF(U38="",(M38*O38)-R38+T38,U38) -> 10.28 | W38: Card | X38: =IF(W38="","Card",W38) -> Card
A39: 120037 | B39: 201 | C39: 45783 | D39: 0.5084838 | E39: 45783 | F39: =TEXT(Table1[[#This Row],[Business_Day]],"dddd") -> Tuesday | G39: Lunch | H39: Drive-Thru | I39: =IF(H39="","Unknown",H39) -> Drive-Thru | J39: Chicken Sandwich Combo | K39: Spicy | L39: =IF(K39="","No Modifier",K39) -> Spicy | M39: 1 | N39: 8.01 | O39: =(V39-T39+R39)/M39 -> 8.01 | P39: =PRODUCT(M39,O39) -> 8.01 | Q39: 0 | R39: =IF(ISBLANK(Q39),ROUND((M39*O39)+T39-V39,2),Q39) -> 0 | S39: 0.58 | T39: =IF(S39="",V39-P39+R39,S39) -> 0.58 | U39: 8.59 | V39: =IF(U39="",(M39*O39)-R39+T39,U39) -> 8.59 | W39: Card | X39: =IF(W39="","Card",W39) -> Card
A40: 120038 | B40: 101 | C40: 45808 | D40: 0.53064815 | E40: 45808 | F40: =TEXT(Table1[[#This Row],[Business_Day]],"dddd") -> Saturday | G40: Late Night | H40: Drive-Thru | I40: =IF(H40="","Unknown",H40) -> Drive-Thru | J40: Cheeseburger | L40: =IF(K40="","No Modifier",K40) -> No Modifier | M40: 1 | N40: 4.05 | O40: =(V40-T40+R40)/M40 -> 4.05 | P40: =PRODUCT(M40,O40) -> 4.05 | Q40: 0 | R40: =IF(ISBLANK(Q40),ROUND((M40*O40)+T40-V40,2),Q40) -> 0 | S40: 0.32 | T40: =IF(S40="",V40-P40+R40,S40) -> 0.32 | U40: 4.37 | V40: =IF(U40="",(M40*O40)-R40+T40,U40) -> 4.37 | W40: Cash | X40: =IF(W40="","Card",W40) -> Cash
A41: 120039 | B41: 401 | C41: 45805 | D41: 0.4646875 | E41: 45805 | F41: =TEXT(Table1[[#This Row],[Business_Day]],"dddd") -> Wednesday | G41: Lunch | H41: Drive-Thru | I41: =IF(H41="","Unknown",H41) -> Drive-Thru | J41: Cheeseburger | L41: =IF(K41="","No Modifier",K41) -> No Modifier | M41: 1 | N41: 4.56 | O41: =(V41-T41+R41)/M41 -> 4.56 | P41: =PRODUCT(M41,O41) -> 4.56 | Q41: 0 | R41: =IF(ISBLANK(Q41),ROUND((M41*O41)+T41-V41,2),Q41) -> 0 | S41: 0.33 | T41: =IF(S41="",V41-P41+R41,S41) -> 0.33 | U41: 4.89 | V41: =IF(U41="",(M41*O41)-R41+T41,U41) -> 4.89 | W41: MobilePay | X41: =IF(W41="","Card",W41) -> MobilePay
A42: 120040 | B42: 401 | C42: 45799 | D42: 0.48596065 | E42: 45799 | F42: =TEXT(Table1[[#This Row],[Business_Day]],"dddd") -> Thursday | G42: Lunch | H42: Dine-In | I42: =IF(H42="","Unknown",H42) -> Dine-In | J42: Chicken Sandwich Combo | L42: =IF(K42="","No Modifier",K42) -> No Modifier | M42: 1 | N42: 9.36 | O42: =(V42-T42+R42)/M42 -> 9.36 | P42: =PRODUCT(M42,O42) -> 9.36 | Q42: 0 | R42: =IF(ISBLANK(Q42),ROUND((M42*O42)+T42-V42,2),Q42) -> 0 | S42: 0.89 | T42: =IF(S42="",V42-P42+R42,S42) -> 0.89 | U42: 10.25 | V42: =IF(U42="",(M42*O42)-R42+T42,U42) -> 10.25 | X42: =IF(W42="","Card",W42) -> Card
A43: 120041 | B43: 201 | C43: 45842 | D43: 0.086608796 | E43: 45842 | F43: =TEXT(Table1[[#This Row],[Business_Day]],"dddd") -> Friday | G43: Lunch | H43: Dine-In | I43: =IF(H43="","Unknown",H43) -> Dine-In | J43: Double Cheeseburger Combo | L43: =IF(K43="","No Modifier",K43) -> No Modifier | M43: 1 | N43: 10.08 | O43: =(V43-T43+R43)/M43 -> 10.08 | P43: =PRODUCT(M43,O43) -> 10.08 | Q43: 0 | R43: =IF(ISBLANK(Q43),ROUND((M43*O43)+T43-V43,2),Q43) -> 0 | S43: 0.66 | T43: =IF(S43="",V43-P43+R43,S43) -> 0.66 | U43: 10.74 | V43: =IF(U43="",(M43*O43)-R43+T43,U43) -> 10.74 | W43: Card | X43: =IF(W43="","Card",W43) -> Card
A44: 120042 | B44: 103 | C44: 45802 | D44: 0.3528588 | E44: 45802 | F44: =TEXT(Table1[[#This Row],[Business_Day]],"dddd") -> Sunday | G44: Dinner | H44: Takeout | I44: =IF(H44="","Unknown",H44) -> Takeout | J44: Cheeseburger Combo | L44: =IF(K44="","No Modifier",K44) -> No Modifier | M44: 1 | N44: 8.43 | O44: =(V44-T44+R44)/M44 -> 8.43 | P44: =PRODUCT(M44,O44) -> 8.43 | Q44: 0 | R44: =IF(ISBLANK(Q44),ROUND((M44*O44)+T44-V44,2),Q44) -> 0 | S44: 0.51 | T44: =IF(S44="",V44-P44+R44,S44) -> 0.51 | U44: 8.94 | V44: =IF(U44="",(M44*O44)-R44+T44,U44) -> 8.94 | W44: Card | X44: =IF(W44="","Card",W44) -> Card
A45: 120043 | B45: 501 | C45: 45876 | D45: 0.2446412 | E45: 45876 | F45: =TEXT(Table1[[#This Row],[Business_Day]],"dddd") -> Thursday | G45: Afternoon | H45: Takeout | I45: =IF(H45="","Unknown",H45) -> Takeout | J45: Chicken Nuggets (10pc) | L45: =IF(K45="","No Modifier",K45) -> No Modifier | M45: 1 | N45: 4.89 | O45: =(V45-T45+R45)/M45 -> 4.89 | P45: =PRODUCT(M45,O45) -> 4.89 | Q45: 0 | R45: =IF(ISBLANK(Q45),ROUND((M45*O45)+T45-V45,2),Q45) -> 0 | S45: 0.42 | T45: =IF(S45="",V45-P45+R45,S45) -> 0.42 | U45: 5.31 | V45: =IF(U45="",(M45*O45)-R45+T45,U45) -> 5.31 | W45: Cash | X45: =IF(W45="","Card",W45) -> Cash
A46: 120044 | B46: 102 | C46: 45836 | D46: 0.40591435 | E46: 45836 | F46: =TEXT(Table1[[#This Row],[Business_Day]],"dddd") -> Saturday | G46: Dinner | I46: =IF(H46="","Unknown",H46) -> Unknown | J46: Double Cheeseburger Combo | L46: =IF(K46="","No Modifier",K46) -> No Modifier | M46: 1 | N46: 9.25 | O46: =(V46-T46+R46)/M46 -> 9.25 | P46: =PRODUCT(M46,O46) -> 9.25 | Q46: 0 | R46: =IF(ISBLANK(Q46),ROUND((M46*O46)+T46-V46,2),Q46) -> 0 | S46: 0.74 | T46: =IF(S46="",V46-P46+R46,S46) -> 0.74 | U46: 9.99 | V46: =IF(U46="",(M46*O46)-R46+T46,U46) -> 9.99 | W46: MobilePay | X46: =IF(W46="","Card",W46) -> MobilePay
A47: 120045 | B47: 403 | C47: 45872 | D47: 0.52318287 | E47: 45872 | F47: =TEXT(Table1[[#This Row],[Business_Day]],"dddd") -> Sunday | G47: Lunch | H47: Delivery | I47: =IF(H47="","Unknown",H47) -> Delivery | J47: Cheeseburger Combo | L47: =IF(K47="","No Modifier",K47) -> No Modifier | M47: 1 | N47: 8.13 | O47: =(V47-T47+R47)/M47 -> 8.13 | P47: =PRODUCT(M47,O47) -> 8.13 | Q47: 0 | R47: =IF(ISBLANK(Q47),ROUND((M47*O47)+T47-V47,2),Q47) -> 0 | S47: 0.61 | T47: =IF(S47="",V47-P47+R47,S47) -> 0.61 | U47: 8.74 | V47: =IF(U47="",(M47*O47)-R47+T47,U47) -> 8.74 | W47: Card | X47: =IF(W47="","Card",W47) -> Card
A48: 120046 | B48: 201 | C48: 45839 | D48: 0.27460648 | E48: 45839 | F48: =TEXT(Table1[[#This Row],[Business_Day]],"dddd") -> Tuesday | G48: Dinner | H48: Dine-In | I48: =IF(H48="","Unknown",H48) -> Dine-In | J48: Onion Rings | K48: Large Size | L48: =IF(K48="","No Modifier",K48) -> Large Size | M48: 1 | N48: 3.01 | O48: =(V48-T48+R48)/M48 -> 3.61 | P48: =PRODUCT(M48,O48) -> 3.61 | Q48: 0 | R48: =IF(ISBLANK(Q48),ROUND((M48*O48)+T48-V48,2),Q48) -> 0 | S48: 0.27 | T48: =IF(S48="",V48-P48+R48,S48) -> 0.27 | U48: 3.88 | V48: =IF(U48="",(M48*O48)-R48+T48,U48) -> 3.88 | W48: GiftCard | X48: =IF(W48="","Card",W48) -> GiftCard
A49: 120047 | B49: 403 | C49: 45854 | D49: 0.3977662 | E49: 45854 | F49: =TEXT(Table1[[#This Row],[Business_Day]],"dddd") -> Wednesday | G49: Breakfast | H49: Drive-Thru | I49: =IF(H49="","Unknown",H49) -> Drive-Thru | J49: Hash Browns | K49: Cinnamon | L49: =IF(K49="","No Modifier",K49) -> Cinnamon | M49: 1 | N49: 2.1 | O49: =(V49-T49+R49)/M49 -> 2.2 | P49: =PRODUCT(M49,O49) -> 2.2 | Q49: 0 | R49: =IF(ISBLANK(Q49),ROUND((M49*O49)+T49-V49,2),Q49) -> 0 | S49: 0.16 | T49: =IF(S49="",V49-P49+R49,S49) -> 0.16 | U49: 2.36 | V49: =IF(U49="",(M49*O49)-R49+T49,U49) -> 2.36 | W49: MobilePay | X49: =IF(W49="","Card",W49) -> MobilePay
A50: 120048 | B50: 402 | C50: 45821 | D50: 0.39052083 | E50: 45821 | F50: =TEXT(Table1[[#This Row],[Business_Day]],"dddd") -> Friday | G50: Dinner | H50: Delivery | I50: =IF(H50="","Unknown",H50) -> Delivery | J50: Cheeseburger Combo | L50: =IF(K50="","No Modifier",K50) -> No Modifier | M50: 1 | N50: 8.66 | O50: =(V50-T50+R50)/M50 -> 8.66 | P50: =PRODUCT(M50,O50) -> 8.66 | Q50: 0 | R50: =IF(ISBLANK(Q50),ROUND((M50*O50)+T50-V50,2),Q50) -> 0 | S50: 0.74 | T50: =IF(S50="",V50-P50+R50,S50) -> 0.74 | U50: 9.4 | V50: =IF(U50="",(M50*O50)-R50+T50,U50) -> 9.4 | W50: Card | X50: =IF(W50="","Card",W50) -> Card
A51: 120049 | B51: 401 | C51: 45794 | D51: 0.52155093 | E51: 45794 | F51: =TEXT(Table1[[#This Row],[Business_Day]],"dddd") -> Saturday | G51: Lunch | H51: Dine-In | I51: =IF(H51="","Unknown",H51) -> Dine-In | J51: Spicy Chicken Sandwich | L51: =IF(K51="","No Modifier",K51) -> No Modifier | M51: 2 | N51: 4.96 | O51: =(V51-T51+R51)/M51 -> 4.96 | P51: =PRODUCT(M51,O51) -> 9.92 | Q51: 1.98 | R51: =IF(ISBLANK(Q51),ROUND((M51*O51)+T51-V51,2),Q51) -> 1.98 | S51: 0.48 | T51: =IF(S51="",V51-P51+R51,S51) -> 0.48 | U51: 8.42 | V51: =IF(U51="",(M51*O51)-R51+T51,U51) -> 8.42 | W51: GiftCard | X51: =IF(W51="","Card",W51) -> GiftCard
A52: 120050 | B52: 202 | C52: 45790 | D52: 0.11186343 | E52: 45790 | F52: =TEXT(Table1[[#This Row],[Business_Day]],"dddd") -> Tuesday | G52: Lunch | H52: Drive-Thru | I52: =IF(H52="","Unknown",H52) -> Drive-Thru | J52: French Fries | K52: No Sauce | L52: =IF(K52="","No Modifier",K52) -> No Sauce | M52: 1 | N52: 2.73 | O52: =(V52-T52+R52)/M52 -> 2.73 | P52: =PRODUCT(M52,O52) -> 2.73 | Q52: 0 | R52: =IF(ISBLANK(Q52),ROUND((M52*O52)+T52-V52,2),Q52) -> 0 | S52: 0.25 | T52: =IF(S52="",V52-P52+R52,S52) -> 0.25 | U52: 2.98 | V52: =IF(U52="",(M52*O52)-R52+T52,U52) -> 2.98 | W52: MobilePay | X52: =IF(W52="","Card",W52) -> MobilePay
A53: 120051 | B53: 201 | C53: 45823 | D53: 0.2837963 | E53: 45823 | F53: =TEXT(Table1[[#This Row],[Business_Day]],"dddd") -> Sunday | G53: Dinner | H53: Delivery | I53: =IF(H53="","Unknown",H53) -> Delivery | J53: Chicken Sandwich | L53: =IF(K53="","No Modifier",K53) -> No Modifier | M53: 1 | N53: 5.25 | O53: =(V53-T53+R53)/M53 -> 5.25 | P53: =PRODUCT(M53,O53) -> 5.25 | Q53: 0 | R53: =IF(ISBLANK(Q53),ROUND((M53*O53)+T53-V53,2),Q53) -> 0 | S53: 0.32 | T53: =IF(S53="",V53-P53+R53,S53) -> 0.32 | U53: 5.57 | V53: =IF(U53="",(M53*O53)-R53+T53,U53) -> 5.57 | W53: Card | X53: =IF(W53="","Card",W53) -> Card
A54: 120052 | B54: 103 | C54: 45868 | D54: 0.41347222 | E54: 45868 | F54: =TEXT(Table1[[#This Row],[Business_Day]],"dddd") -> Wednesday | G54: Breakfast | H54: Drive-Thru | I54: =IF(H54="","Unknown",H54) -> Drive-Thru | J54: Soft Drink (Small) | L54: =IF(K54="","No Modifier",K54) -> No Modifier | M54: 1 | N54: 1.48 | O54: =(V54-T54+R54)/M54 -> 1.48 | P54: =PRODUCT(M54,O54) -> 1.48 | Q54: 0 | R54: =IF(ISBLANK(Q54),ROUND((M54*O54)+T54-V54,2),Q54) -> 0 | S54: 0.11 | T54: =IF(S54="",V54-P54+R54,S54) -> 0.11 | U54: 1.59 | V54: =IF(U54="",(M54*O54)-R54+T54,U54) -> 1.59 | W54: Card | X54: =IF(W54="","Card",W54) -> Card
A55: 120053 | B55: 102 | C55: 45834 | D55: 0.069756944 | E55: 45834 | F55: =TEXT(Table1[[#This Row],[Business_Day]],"dddd") -> Thursday | G55: Lunch | H55: Delivery | I55: =IF(H55="","Unknown",H55) -> Delivery | J55: Spicy Chicken Sandwich | K55: Extra Patty | L55: =IF(K55="","No Modifier",K55) -> Extra Patty | M55: 1 | N55: 5.87 | O55: =(V55-T55+R55)/M55 -> 7.87 | P55: =PRODUCT(M55,O55) -> 7.87 | Q55: 0 | R55: =IF(ISBLANK(Q55),ROUND((M55*O55)+T55-V55,2),Q55) -> 0 | S55: 0.63 | T55: =IF(S55="",V55-P55+R55,S55) -> 0.63 | U55: 8.5 | V55: =IF(U55="",(M55*O55)-R55+T55,U55) -> 8.5 | W55: Card | X55: =IF(W55="","Card",W55) -> Card
A56: 120054 | B56: 202 | C56: 45768 | D56: 0.45123843 | E56: 45768 | F56: =TEXT(Table1[[#This Row],[Business_Day]],"dddd") -> Monday | G56: Breakfast | H56: Drive-Thru | I56: =IF(H56="","Unknown",H56) -> Drive-Thru | J56: Coffee | K56: Extra Ice | L56: =IF(K56="","No Modifier",K56) -> Extra Ice | M56: 1 | N56: 2.1 | O56: =(V56-T56+R56)/M56 -> 2.1 | P56: =PRODUCT(M56,O56) -> 2.1 | Q56: 0 | R56: =IF(ISBLANK(Q56),ROUND((M56*O56)+T56-V56,2),Q56) -> 0 | S56: 0.17 | T56: =IF(S56="",V56-P56+R56,S56) -> 0.17 | U56: 2.27 | V56: =IF(U56="",(M56*O56)-R56+T56,U56) -> 2.27 | W56: MobilePay | X56: =IF(W56="","Card",W56) -> MobilePay
A57: 120055 | B57: 103 | C57: 45763 | D57: 0.2368287 | E57: 45763 | F57: =TEXT(Table1[[#This Row],[Business_Day]],"dddd") -> Wednesday | G57: Afternoon | H57: Takeout | I57: =IF(H57="","Unknown",H57) -> Takeout | J57: Iced Tea | L57: =IF(K57="","No Modifier",K57) -> No Modifier | M57: 2 | N57: 2.01 | O57: =(V57-T57+R57)/M57 -> 2.01 | P57: =PRODUCT(M57,O57) -> 4.02 | Q57: 0 | R57: =IF(ISBLANK(Q57),ROUND((M57*O57)+T57-V57,2),Q57) -> 0 | S57: 0.34 | T57: =IF(S57="",V57-P57+R57,S57) -> 0.34 | U57: 4.36 | V57: =IF(U57="",(M57*O57)-R57+T57,U57) -> 4.36 | W57: Card | X57: =IF(W57="","Card",W57) -> Card
A58: 120056 | B58: 202 | C58: 45846 | D58: 0.410625 | E58: 45846 | F58: =TEXT(Table1[[#This Row],[Business_Day]],"dddd") -> Tuesday | G58: Dinner | H58: Drive-Thru | I58: =IF(H58="","Unknown",H58) -> Drive-Thru | J58: Double Cheeseburger | L58: =IF(K58="","No Modifier",K58) -> No Modifier | M58: 1 | N58: 5.39 | O58: =(V58-T58+R58)/M58 -> 5.39 | P58: =PRODUCT(M58,O58) -> 5.39 | Q58: 0 | R58: =IF(ISBLANK(Q58),ROUND((M58*O58)+T58-V58,2),Q58) -> 0 | S58: 0.46 | T58: =IF(S58="",V58-P58+R58,S58) -> 0.46 | U58: 5.85 | V58: =IF(U58="",(M58*O58)-R58+T58,U58) -> 5.85 | W58: Card | X58: =IF(W58="","Card",W58) -> Card
A59: 120057 | B59: 403 | C59: 45831 | D59: 0.44980324 | E59: 45831 | F59: =TEXT(Table1[[#This Row],[Business_Day]],"dddd") -> Monday | G59: Breakfast | H59: Takeout | I59: =IF(H59="","Unknown",H59) -> Takeout | J59: Pancake Platter | K59: No Cheese | L59: =IF(K59="","No Modifier",K59) -> No Cheese | M59: 1 | N59: 4.89 | O59: =(V59-T59+R59)/M59 -> 4.89 | P59: =PRODUCT(M59,O59) -> 4.89 | Q59: 0 | R59: =IF(ISBLANK(Q59),ROUND((M59*O59)+T59-V59,2),Q59) -> 0 | S59: 0.46 | T59: =IF(S59="",V59-P59+R59,S59) -> 0.46 | U59: 5.35 | V59: =IF(U59="",(M59*O59)-R59+T59,U59) -> 5.35 | W59: Card | X59: =IF(W59="","Card",W59) -> Card
A60: 120058 | B60: 202 | C60: 45864 | D60: 0.12641204 | E60: 45864 | F60: =TEXT(Table1[[#This Row],[Business_Day]],"dddd") -> Saturday | G60: Afternoon | H60: Takeout | I60: =IF(H60="","Unknown",H60) -> Takeout | J60: Chicken Nuggets (6pc) | L60: =IF(K60="","No Modifier",K60) -> No Modifier | M60: 1 | N60: 3.82 | O60: =(V60-T60+R60)/M60 -> 3.82 | P60: =PRODUCT(M60,O60) -> 3.82 | Q60: 0 | R60: =IF(ISBLANK(Q60),ROUND((M60*O60)+T60-V60,2),Q60) -> 0 | S60: 0.36 | T60: =IF(S60="",V60-P60+R60,S60) -> 0.36 | U60: 4.18 | V60: =IF(U60="",(M60*O60)-R60+T60,U60) -> 4.18 | W60: Card | X60: =IF(W60="","Card",W60) -> Card
A61: 120059 | B61: 402 | C61: 45758 | D61: 0.16856481 | E61: 45758 | F61: =TEXT(Table1[[#This Row],[Business_Day]],"dddd") -> Friday | G61: Afternoon | H61: Takeout | I61: =IF(H61="","Unknown",H61) -> Takeout | J61: Ice Cream Cone | L61: =IF(K61="","No Modifier",K61) -> No Modifier | M61: 3 | N61: 1.75 | O61: =(V61-T61+R61)/M61 -> 2.25 | P61: =PRODUCT(M61,O61) -> 6.75 | Q61: 0 | R61: =IF(ISBLANK(Q61),ROUND((M61*O61)+T61-V61,2),Q61) -> 0 | S61: 0.54 | T61: =IF(S61="",V61-P61+R61,S61) -> 0.54 | U61: 7.29 | V61: =IF(U61="",(M61*O61)-R61+T61,U61) -> 7.29 | W61: Card | X61: =IF(W61="","Card",W61) -> Card
A62: 120060 | B62: 102 | C62: 45796 | D62: 0.2347338 | E62: 45796 | F62: =TEXT(Table1[[#This Row],[Business_Day]],"dddd") -> Monday | G62: Afternoon | H62: Dine-In | I62: =IF(H62="","Unknown",H62) -> Dine-In | J62: Ice Cream Cone | K62: Caramel Topping | L62: =IF(K62="","No Modifier",K62) -> Caramel Topping | M62: 1 | N62: 1.58 | O62: =(V62-T62+R62)/M62 -> 2.08 | P62: =PRODUCT(M62,O62) -> 2.08 | Q62: 0 | R62: =IF(ISBLANK(Q62),ROUND((M62*O62)+T62-V62,2),Q62) -> 0 | S62: 0.15 | T62: =IF(S62="",V62-P62+R62,S62) -> 0.15 | U62: 2.23 | V62: =IF(U62="",(M62*O62)-R62+T62,U62) -> 2.23 | W62: Card | X62: =IF(W62="","Card",W62) -> Card
A63: 120061 | B63: 501 | C63: 45769 | D63: 0.25594907 | E63: 45769 | F63: =TEXT(Table1[[#This Row],[Business_Day]],"dddd") -> Tuesday | G63: Breakfast | H63: Takeout | I63: =IF(H63="","Unknown",H63) -> Takeout | J63: Pancake Platter | L63: =IF(K63="","No Modifier",K63) -> No Modifier | M63: 1 | N63: 4.93 | O63: =(V63-T63+R63)/M63 -> 4.93 | P63: =PRODUCT(M63,O63) -> 4.93 | Q63: 0 | R63: =IF(ISBLANK(Q63),ROUND((M63*O63)+T63-V63,2),Q63) -> 0 | S63: 0.36 | T63: =IF(S63="",V63-P63+R63,S63) -> 0.36 | U63: 5.29 | V63: =IF(U63="",(M63*O63)-R63+T63,U63) -> 5.29 | X63: =IF(W63="","Card",W63) -> Card
A64: 120062 | B64: 102 | C64: 45818 | D64: 0.40929398 | E64: 45818 | F64: =TEXT(Table1[[#This Row],[Business_Day]],"dddd") -> Tuesday | G64: Dinner | H64: Takeout | I64: =IF(H64="","Unknown",H64) -> Takeout | J64: Cheeseburger Combo | L64: =IF(K64="","No Modifier",K64) -> No Modifier | M64: 1 | N64: 7.94 | O64: =(V64-T64+R64)/M64 -> 7.94 | P64: =PRODUCT(M64,O64) -> 7.94 | Q64: 0 | R64: =IF(ISBLANK(Q64),ROUND((M64*O64)+T64-V64,2),Q64) -> 0 | S64: 0.75 | T64: =IF(S64="",V64-P64+R64,S64) -> 0.75 | U64: 8.69 | V64: =IF(U64="",(M64*O64)-R64+T64,U64) -> 8.69 | W64: Card | X64: =IF(W64="","Card",W64) -> Card
A65: 120063 | B65: 401 | C65: 45816 | D65: 0.24893519 | E65: 45816 | F65: =TEXT(Table1[[#This Row],[Business_Day]],"dddd") -> Sunday | G65: Afternoon | H65: Dine-In | I65: =IF(H65="","Unknown",H65) -> Dine-In | J65: Iced Tea | L65: =IF(K65="","No Modifier",K65) -> No Modifier | M65: 1 | N65: 1.73 | O65: =(V65-T65+R65)/M65 -> 1.73 | P65: =PRODUCT(M65,O65) -> 1.73 | Q65: 0 | R65: =IF(ISBLANK(Q65),ROUND((M65*O65)+T65-V65,2),Q65) -> 0 | S65: 0.16 | T65: =IF(S65="",V65-P65+R65,S65) -> 0.16 | U65: 1.89 | V65: =IF(U65="",(M65*O65)-R65+T65,U65) -> 1.89 | W65: Card | X65: =IF(W65="","Card",W65) -> Card
A66: 120064 | B66: 401 | C66: 45789 | D66: 0.24630787 | E66: 45789 | F66: =TEXT(Table1[[#This Row],[Business_Day]],"dddd") -> Monday | G66: Breakfast | H66: Drive-Thru | I66: =IF(H66="","Unknown",H66) -> Drive-Thru | J66: Coffee | L66: =IF(K66="","No Modifier",K66) -> No Modifier | M66: 1 | N66: 2.05 | O66: =(V66-T66+R66)/M66 -> 2.05 | P66: =PRODUCT(M66,O66) -> 2.05 | Q66: 0 | R66: =IF(ISBLANK(Q66),ROUND((M66*O66)+T66-V66,2),Q66) -> 0 | S66: 0.16 | T66: =IF(S66="",V66-P66+R66,S66) -> 0.16 | U66: 2.21 | V66: =IF(U66="",(M66*O66)-R66+T66,U66) -> 2.21 | W66: Cash | X66: =IF(W66="","Card",W66) -> Cash
A67: 120065 | B67: 202 | C67: 45859 | D67: 0.086168981 | E67: 45859 | F67: =TEXT(Table1[[#This Row],[Business_Day]],"dddd") -> Monday | G67: Lunch | H67: Drive-Thru | I67: =IF(H67="","Unknown",H67) -> Drive-Thru | J67: Cheeseburger | L67: =IF(K67="","No Modifier",K67) -> No Modifier | M67: 1 | N67: 4.94 | O67: =(V67-T67+R67)/M67 -> 4.94 | P67: =PRODUCT(M67,O67) -> 4.94 | Q67: 0 | R67: =IF(ISBLANK(Q67),ROUND((M67*O67)+T67-V67,2),Q67) -> 0 | S67: 0.47 | T67: =IF(S67="",V67-P67+R67,S67) -> 0.47 | U67: 5.41 | V67: =IF(U67="",(M67*O67)-R67+T67,U67) -> 5.41 | W67: Card | X67: =IF(W67="","Card",W67) -> Card
A68: 120066 | B68: 401 | C68: 45786 | D68: 0.26293981 | E68: 45786 | F68: =TEXT(Table1[[#This Row],[Business_Day]],"dddd") -> Friday | G68: Dinner | H68: Dine-In | I68: =IF(H68="","Unknown",H68) -> Dine-In | J68: Cheeseburger Combo | L68: =IF(K68="","No Modifier",K68) -> No Modifier | M68: 1 | N68: 8.45 | O68: =(V68-T68+R68)/M68 -> 8.45 | P68: =PRODUCT(M68,O68) -> 8.45 | Q68: 0 | R68: =IF(ISBLANK(Q68),ROUND((M68*O68)+T68-V68,2),Q68) -> 0 | S68: 0.68 | T68: =IF(S68="",V68-P68+R68,S68) -> 0.68 | U68: 9.13 | V68: =IF(U68="",(M68*O68)-R68+T68,U68) -> 9.13 | W68: Card | X68: =IF(W68="","Card",W68) -> Card
A69: 120067 | B69: 403 | C69: 45774 | D69: 0.44373843 | E69: 45774 | F69: =TEXT(Table1[[#This Row],[Business_Day]],"dddd") -> Sunday | G69: Late Night | H69: Drive-Thru | I69: =IF(H69="","Unknown",H69) -> Drive-Thru | J69: Cheeseburger | L69: =IF(K69="","No Modifier",K69) -> No Modifier | M69: 1 | N69: 4.82 | O69: =(V69-T69+R69)/M69 -> 4.82 | P69: =PRODUCT(M69,O69) -> 4.82 | Q69: 0 | R69: =IF(ISBLANK(Q69),ROUND((M69*O69)+T69-V69,2),Q69) -> 0 | S69: 0.39 | T69: =IF(S69="",V69-P69+R69,S69) -> 0.39 | U69: 5.21 | V69: =IF(U69="",(M69*O69)-R69+T69,U69) -> 5.21 | W69: Cash | X69: =IF(W69="","Card",W69) -> Cash
A70: 120068 | B70: 101 | C70: 45811 | D70: 0.26696759 | E70: 45811 | F70: =TEXT(Table1[[#This Row],[Business_Day]],"dddd") -> Tuesday | G70: Breakfast | H70: Takeout | I70: =IF(H70="","Unknown",H70) -> Takeout | J70: Sausage Biscuit | L70: =IF(K70="","No Modifier",K70) -> No Modifier | M70: 2 | N70: 3.13 | O70: =(V70-T70+R70)/M70 -> 3.13 | P70: =PRODUCT(M70,O70) -> 6.26 | Q70: 0 | R70: =IF(ISBLANK(Q70),ROUND((M70*O70)+T70-V70,2),Q70) -> 0 | S70: 0.38 | T70: =IF(S70="",V70-P70+R70,S70) -> 0.38 | U70: 6.64 | V70: =IF(U70="",(M70*O70)-R70+T70,U70) -> 6.64 | W70: Card | X70: =IF(W70="","Card",W70) -> Card
A71: 120069 | B71: 401 | C71: 45822 | D71: 0.095289352 | E71: 45822 | F71: =TEXT(Table1[[#This Row],[Business_Day]],"dddd") -> Saturday | G71: Lunch | H71: Drive-Thru | I71: =IF(H71="","Unknown",H71) -> Drive-Thru | J71: Cheeseburger Combo | L71: =IF(K71="","No Modifier",K71) -> No Modifier | M71: 1 | N71: 8.17 | O71: =(V71-T71+R71)/M71 -> 8.32 | P71: =PRODUCT(M71,O71) -> 8.32 | R71: =IF(ISBLANK(Q71),ROUND((M71*O71)+T71-V71,2),Q71) -> 0.15 | S71: 0.61 | T71: =IF(S71="",V71-P71+R71,S71) -> 0.61 | U71: 8.78 | V71: =IF(U71="",(M71*O71)-R71+T71,U71) -> 8.78 | W71: Card | X71: =IF(W71="","Card",W71) -> Card
A72: 120070 | B72: 201 | C72: 45781 | D72: 0.34606481 | E72: 45781 | F72: =TEXT(Table1[[#This Row],[Business_Day]],"dddd") -> Sunday | G72: Dinner | H72: Dine-In | I72: =IF(H72="","Unknown",H72) -> Dine-In | J72: Cheeseburger Combo | L72: =IF(K72="","No Modifier",K72) -> No Modifier | M72: 1 | N72: 8.67 | O72: =(V72-T72+R72)/M72 -> 8.67 | P72: =PRODUCT(M72,O72) -> 8.67 | Q72: 0 | R72: =IF(ISBLANK(Q72),ROUND((M72*O72)+T72-V72,2),Q72) -> 0 | S72: 0.82 | T72: =IF(S72="",V72-P72+R72,S72) -> 0.82 | U72: 9.49 | V72: =IF(U72="",(M72*O72)-R72+T72,U72) -> 9.49 | W72: Card | X72: =IF(W72="","Card",W72) -> Card
A73: 120071 | B73: 101 | C73: 45869 | D73: 0.066979167 | E73: 45869 | F73: =TEXT(Table1[[#This Row],[Business_Day]],"dddd") -> Thursday | G73: Lunch | H73: Takeout | I73: =IF(H73="","Unknown",H73) -> Takeout | J73: Cheeseburger Combo | L73: =IF(K73="","No Modifier",K73) -> No Modifier | M73: 1 | N73: 9.26 | O73: =(V73-T73+R73)/M73 -> 9.26 | P73: =PRODUCT(M73,O73) -> 9.26 | Q73: 0 | R73: =IF(ISBLANK(Q73),ROUND((M73*O73)+T73-V73,2),Q73) -> 0 | S73: 0.83 | T73: =IF(S73="",V73-P73+R73,S73) -> 0.83 | U73: 10.09 | V73: =IF(U73="",(M73*O73)-R73+T73,U73) -> 10.09 | W73: Cash | X73: =IF(W73="","Card",W73) -> Cash
A74: 120072 | B74: 501 | C74: 45868 | D74: 0.12174769 | E74: 45868 | F74: =TEXT(Table1[[#This Row],[Business_Day]],"dddd") -> Wednesday | G74: Lunch | H74: Drive-Thru | I74: =IF(H74="","Unknown",H74) -> Drive-Thru | J74: Double Cheeseburger Combo | L74: =IF(K74="","No Modifier",K74) -> No Modifier | M74: 1 | N74: 9.97 | O74: =(V74-T74+R74)/M74 -> 9.97 | P74: =PRODUCT(M74,O74) -> 9.97 | Q74: 0 | R74: =IF(ISBLANK(Q74),ROUND((M74*O74)+T74-V74,2),Q74) -> 0 | S74: 0.72 | T74: =IF(S74="",V74-P74+R74,S74) -> 0.72 | U74: 10.69 | V74: =IF(U74="",(M74*O74)-R74+T74,U74) -> 10.69 | W74: Card | X74: =IF(W74="","Card",W74) -> Card
A75: 120073 | B75: 201 | C75: 45846 | D75: 0.2580787 | E75: 45846 | F75: =TEXT(Table1[[#This Row],[Business_Day]],"dddd") -> Tuesday | G75: Breakfast | H75: Dine-In | I75: =IF(H75="","Unknown",H75) -> Dine-In | J75: Egg Muffin | K75: Cinnamon | L75: =IF(K75="","No Modifier",K75) -> Cinnamon | M75: 1 | N75: 3.63 | O75: =(V75-T75+R75)/M75 -> 3.73 | P75: =PRODUCT(M75,O75) -> 3.73 | Q75: 0 | R75: =IF(ISBLANK(Q75),ROUND((M75*O75)+T75-V75,2),Q75) -> 0 | S75: 0.34 | T75: =IF(S75="",V75-P75+R75,S75) -> 0.34 | U75: 4.07 | V75: =IF(U75="",(M75*O75)-R75+T75,U75) -> 4.07 | W75: MobilePay | X75: =IF(W75="","Card",W75) -> MobilePay
A76: 120074 | B76: 301 | C76: 45870 | D76: 0.35324074 | E76: 45870 | F76: =TEXT(Table1[[#This Row],[Business_Day]],"dddd") -> Friday | G76: Breakfast | H76: Takeout | I76: =IF(H76="","Unknown",H76) -> Takeout | J76: Egg Muffin | L76: =IF(K76="","No Modifier",K76) -> No Modifier | M76: 1 | N76: 2.59 | O76: =(V76-T76+R76)/M76 -> 3.79 | P76: =PRODUCT(M76,O76) -> 3.79 | Q76: 0.57 | R76: =IF(ISBLANK(Q76),ROUND((M76*O76)+T76-V76,2),Q76) -> 0.57 | S76: 0.24 | T76: =IF(S76="",V76-P76+R76,S76) -> 0.24 | U76: 3.46 | V76: =IF(U76="",(M76*O76)-R76+T76,U76) -> 3.46 | W76: Card | X76: =IF(W76="","Card",W76) -> Card
A77: 120075 | B77: 402 | C77: 45777 | D77: 0.24793981 | E77: 45777 | F77: =TEXT(Table1[[#This Row],[Business_Day]],"dddd") -> Wednesday | G77: Afternoon | H77: Takeout | I77: =IF(H77="","Unknown",H77) -> Takeout | J77: Milkshake | L77: =IF(K77="","No Modifier",K77) -> No Modifier | M77: 1 | N77: 4.26 | O77: =(V77-T77+R77)/M77 -> 4.26 | P77: =PRODUCT(M77,O77) -> 4.26 | Q77: 0 | R77: =IF(ISBLANK(Q77),ROUND((M77*O77)+T77-V77,2),Q77) -> 0 | S77: 0.26 | T77: =IF(S77="",V77-P77+R77,S77) -> 0.26 | U77: 4.52 | V77: =IF(U77="",(M77*O77)-R77+T77,U77) -> 4.52 | W77: MobilePay | X77: =IF(W77="","Card",W77) -> MobilePay
A78: 120076 | B78: 103 | C78: 45788 | D78: 0.35315972 | E78: 45788 | F78: =TEXT(Table1[[#This Row],[Business_Day]],"dddd") -> Sunday | G78: Breakfast | H78: Delivery | I78: =IF(H78="","Unknown",H78) -> Delivery | J78: Sausage Biscuit | L78: =IF(K78="","No Modifier",K78) -> No Modifier | M78: 1 | N78: 3.06 | O78: =(V78-T78+R78)/M78 -> 3.06 | P78: =PRODUCT(M78,O78) -> 3.06 | Q78: 0 | R78: =IF(ISBLANK(Q78),ROUND((M78*O78)+T78-V78,2),Q78) -> 0 | S78: 0.18 | T78: =IF(S78="",V78-P78+R78,S78) -> 0.18 | U78: 3.24 | V78: =IF(U78="",(M78*O78)-R78+T78,U78) -> 3.24 | W78: Card | X78: =IF(W78="","Card",W78) -> Card
A79: 120077 | B79: 202 | C79: 45769 | D79: 0.43130787 | E79: 45769 | F79: =TEXT(Table1[[#This Row],[Business_Day]],"dddd") -> Tuesday | G79: Morning | H79: Takeout | I79: =IF(H79="","Unknown",H79) -> Takeout | J79: Latte | K79: Almond Milk | L79: =IF(K79="","No Modifier",K79) -> Almond Milk | M79: 1 | N79: 3.17 | O79: =(V79-T79+R79)/M79 -> 3.87 | P79: =PRODUCT(M79,O79) -> 3.87 | Q79: 0 | R79: =IF(ISBLANK(Q79),ROUND((M79*O79)+T79-V79,2),Q79) -> 0 | S79: 0.25 | T79: =IF(S79="",V79-P79+R79,S79) -> 0.25 | U79: 4.12 | V79: =IF(U79="",(M79*O79)-R79+T79,U79) -> 4.12 | W79: Card | X79: =IF(W79="","Card",W79) -> Card
A80: 120078 | B80: 403 | C80: 45793 | D80: 0.35582176 | E80: 45793 | F80: =TEXT(Table1[[#This Row],[Business_Day]],"dddd") -> Friday | G80: Breakfast | H80: Dine-In | I80: =IF(H80="","Unknown",H80) -> Dine-In | J80: Milkshake | L80: =IF(K80="","No Modifier",K80) -> No Modifier | M80: 1 | N80: 4.02 | O80: =(V80-T80+R80)/M80 -> 4.02 | P80: =PRODUCT(M80,O80) -> 4.02 | Q80: 0 | R80: =IF(ISBLANK(Q80),ROUND((M80*O80)+T80-V80,2),Q80) -> 0 | S80: 0.28 | T80: =IF(S80="",V80-P80+R80,S80) -> 0.28 | U80: 4.3 | V80: =IF(U80="",(M80*O80)-R80+T80,U80) -> 4.3 | W80: Card | X80: =IF(W80="","Card",W80) -> Card
A81: 120079 | B81: 403 | C81: 45835 | D81: 0.38099537 | E81: 45835 | F81: =TEXT(Table1[[#This Row],[Business_Day]],"dddd") -> Friday | G81: Breakfast | H81: Takeout | I81: =IF(H81="","Unknown",H81) -> Takeout | J81: Latte | K81: Light Ice | L81: =IF(K81="","No Modifier",K81) -> Light Ice | M81: 1 | N81: 2.74 | O81: =(V81-T81+R81)/M81 -> 2.74 | P81: =PRODUCT(M81,O81) -> 2.74 | Q81: 0.41 | R81: =IF(ISBLANK(Q81),ROUND((M81*O81)+T81-V81,2),Q81) -> 0.41 | S81: 0.17 | T81: =IF(S81="",V81-P81+R81,S81) -> 0.17 | U81: 2.5 | V81: =IF(U81="",(M81*O81)-R81+T81,U81) -> 2.5 | W81: Card | X81: =IF(W81="","Card",W81) -> Card
A82: 120080 | B82: 201 | C82: 45775 | D82: 0.12353009 | E82: 45775 | F82: =TEXT(Table1[[#This Row],[Business_Day]],"dddd") -> Monday | G82: Lunch | H82: Dine-In | I82: =IF(H82="","Unknown",H82) -> Dine-In | J82: Chicken Sandwich Combo | K82: Gluten-Free Bun | L82: =IF(K82="","No Modifier",K82) -> Gluten-Free Bun | M82: 1 | N82: 8.88 | O82: =(V82-T82+R82)/M82 -> 9.88 | P82: =PRODUCT(M82,O82) -> 9.88 | Q82: 0 | R82: =IF(ISBLANK(Q82),ROUND((M82*O82)+T82-V82,2),Q82) -> 0 | S82: 0.84 | T82: =IF(S82="",V82-P82+R82,S82) -> 0.84 | U82: 10.72 | V82: =IF(U82="",(M82*O82)-R82+T82,U82) -> 10.72 | W82: Cash | X82: =IF(W82="","Card",W82) -> Cash
A83: 120081 | B83: 402 | C83: 45808 | D83: 0.281875 | E83: 45808 | F83: =TEXT(Table1[[#This Row],[Business_Day]],"dddd") -> Saturday | G83: Dinner | H83: Takeout | I83: =IF(H83="","Unknown",H83) -> Takeout | J83: Double Cheeseburger | L83: =IF(K83="","No Modifier",K83) -> No Modifier | M83: 1 | N83: 5.89 | O83: =(V83-T83+R83)/M83 -> 5.89 | P83: =PRODUCT(M83,O83) -> 5.89 | Q83: 0 | R83: =IF(ISBLANK(Q83),ROUND((M83*O83)+T83-V83,2),Q83) -> 0 | S83: 0.5 | T83: =IF(S83="",V83-P83+R83,S83) -> 0.5 | U83: 6.39 | V83: =IF(U83="",(M83*O83)-R83+T83,U83) -> 6.39 | W83: Card | X83: =IF(W83="","Card",W83) -> Card
A84: 120082 | B84: 401 | C84: 45814 | D84: 0.30236111 | E84: 45814 | F84: =TEXT(Table1[[#This Row],[Business_Day]],"dddd") -> Friday | G84: Breakfast | H84: Drive-Thru | I84: =IF(H84="","Unknown",H84) -> Drive-Thru | J84: Egg Muffin | K84: Sausage Patty | L84: =IF(K84="","No Modifier",K84) -> Sausage Patty | M84: 1 | N84: 3.61 | O84: =(V84-T84+R84)/M84 -> 4.81 | P84: =PRODUCT(M84,O84) -> 4.81 | Q84: 0 | R84: =IF(ISBLANK(Q84),ROUND((M84*O84)+T84-V84,2),Q84) -> 0 | S84: 0.36 | T84: =IF(S84="",V84-P84+R84,S84) -> 0.36 | U84: 5.17 | V84: =IF(U84="",(M84*O84)-R84+T84,U84) -> 5.17 | W84: Card | X84: =IF(W84="","Card",W84) -> Card
A85: 120083 | B85: 501 | C85: 45868 | D85: 0.21959491 | E85: 45868 | F85: =TEXT(Table1[[#This Row],[Business_Day]],"dddd") -> Wednesday | G85: Breakfast | H85: Drive-Thru | I85: =IF(H85="","Unknown",H85) -> Drive-Thru | J85: Coffee | L85: =IF(K85="","No Modifier",K85) -> No Modifier | M85: 1 | N85: 1.79 | O85: =(V85-T85+R85)/M85 -> 1.79 | P85: =PRODUCT(M85,O85) -> 1.79 | Q85: 0 | R85: =IF(ISBLANK(Q85),ROUND((M85*O85)+T85-V85,2),Q85) -> 0 | S85: 0.12 | T85: =IF(S85="",V85-P85+R85,S85) -> 0.12 | U85: 1.91 | V85: =IF(U85="",(M85*O85)-R85+T85,U85) -> 1.91 | W85: Card | X85: =IF(W85="","Card",W85) -> Card
A86: 120084 | B86: 402 | C86: 45876 | D86: 0.23097222 | E86: 45876 | F86: =TEXT(Table1[[#This Row],[Business_Day]],"dddd") -> Thursday | G86: Afternoon | H86: Dine-In | I86: =IF(H86="","Unknown",H86) -> Dine-In | J86: Onion Rings | K86: Small Size | L86: =IF(K86="","No Modifier",K86) -> Small Size | M86: 1 | N86: 2.91 | O86: =(V86-T86+R86)/M86 -> 2.61 | P86: =PRODUCT(M86,O86) -> 2.61 | Q86: 0 | R86: =IF(ISBLANK(Q86),ROUND((M86*O86)+T86-V86,2),Q86) -> 0 | S86: 0.17 | T86: =IF(S86="",V86-P86+R86,S86) -> 0.17 | U86: 2.78 | V86: =IF(U86="",(M86*O86)-R86+T86,U86) -> 2.78 | W86: Card | X86: =IF(W86="","Card",W86) -> Card
A87: 120085 | B87: 403 | C87: 45829 | D87: 0.085185185 | E87: 45829 | F87: =TEXT(Table1[[#This Row],[Business_Day]],"dddd") -> Saturday | G87: Lunch | H87: Takeout | I87: =IF(H87="","Unknown",H87) -> Takeout | J87: Double Cheeseburger Combo | L87: =IF(K87="","No Modifier",K87) -> No Modifier | M87: 1 | N87: 9.74 | O87: =(V87-T87+R87)/M87 -> 9.74 | P87: =PRODUCT(M87,O87) -> 9.74 | Q87: 0 | R87: =IF(ISBLANK(Q87),ROUND((M87*O87)+T87-V87,2),Q87) -> 0 | S87: 0.63 | T87: =IF(S87="",V87-P87+R87,S87) -> 0.63 | U87: 10.37 | V87: =IF(U87="",(M87*O87)-R87+T87,U87) -> 10.37 | W87: Card | X87: =IF(W87="","Card",W87) -> Card
A88: 120086 | B88: 103 | C88: 45791 | D88: 0.40590278 | E88: 45791 | F88: =TEXT(Table1[[#This Row],[Business_Day]],"dddd") -> Wednesday | G88: Dinner | H88: Delivery | I88: =IF(H88="","Unknown",H88) -> Delivery | J88: Cheeseburger | L88: =IF(K88="","No Modifier",K88) -> No Modifier | M88: 1 | N88: 4.8 | O88: =(V88-T88+R88)/M88 -> 4.8 | P88: =PRODUCT(M88,O88) -> 4.8 | Q88: 0 | R88: =IF(ISBLANK(Q88),ROUND((M88*O88)+T88-V88,2),Q88) -> 0 | S88: 0.29 | T88: =IF(S88="",V88-P88+R88,S88) -> 0.29 | U88: 5.09 | V88: =IF(U88="",(M88*O88)-R88+T88,U88) -> 5.09 | W88: MobilePay | X88: =IF(W88="","Card",W88) -> MobilePay
A89: 120087 | B89: 403 | C89: 45874 | D89: 0.51275463 | E89: 45874 | F89: =TEXT(Table1[[#This Row],[Business_Day]],"dddd") -> Tuesday | G89: Lunch | H89: Drive-Thru | I89: =IF(H89="","Unknown",H89) -> Drive-Thru | J89: Spicy Chicken Combo | L89: =IF(K89="","No Modifier",K89) -> No Modifier | M89: 1 | N89: 9.45 | O89: =(V89-T89+R89)/M89 -> 9.45 | P89: =PRODUCT(M89,O89) -> 9.45 | Q89: 0 | R89: =IF(ISBLANK(Q89),ROUND((M89*O89)+T89-V89,2),Q89) -> 0 | S89: 0.8 | T89: =IF(S89="",V89-P89+R89,S89) -> 0.8 | U89: 10.25 | V89: =IF(U89="",(M89*O89)-R89+T89,U89) -> 10.25 | W89: Card | X89: =IF(W89="","Card",W89) -> Card
A90: 120088 | B90: 402 | C90: 45776 | D90: 0.077141204 | E90: 45776 | F90: =TEXT(Table1[[#This Row],[Business_Day]],"dddd") -> Tuesday | G90: Lunch | H90: Drive-Thru | I90: =IF(H90="","Unknown",H90) -> Drive-Thru | J90: Chicken Sandwich Combo | K90: Add Jalapenos | L90: =IF(K90="","No Modifier",K90) -> Add Jalapenos | M90: 1 | N90: 8.73 | O90: =(V90-T90+R90)/M90 -> 9.13 | P90: =PRODUCT(M90,O90) -> 9.13 | Q90: 0 | R90: =IF(ISBLANK(Q90),ROUND((M90*O90)+T90-V90,2),Q90) -> 0 | S90: 0.73 | T90: =IF(S90="",V90-P90+R90,S90) -> 0.73 | U90: 9.86 | V90: =IF(U90="",(M90*O90)-R90+T90,U90) -> 9.86 | W90: Card | X90: =IF(W90="","Card",W90) -> Card
A91: 120089 | B91: 301 | C91: 45785 | D91: 0.0690625 | E91: 45785 | F91: =TEXT(Table1[[#This Row],[Business_Day]],"dddd") -> Thursday | G91: Lunch | H91: Dine-In | I91: =IF(H91="","Unknown",H91) -> Dine-In | J91: Chicken Nuggets (10pc) | L91: =IF(K91="","No Modifier",K91) -> No Modifier | M91: 1 | N91: 5.16 | O91: =(V91-T91+R91)/M91 -> 5.16 | P91: =PRODUCT(M91,O91) -> 5.16 | Q91: 0 | R91: =IF(ISBLANK(Q91),ROUND((M91*O91)+T91-V91,2),Q91) -> 0 | S91: 0.36 | T91: =IF(S91="",V91-P91+R91,S91) -> 0.36 | U91: 5.52 | V91: =IF(U91="",(M91*O91)-R91+T91,U91) -> 5.52 | W91: GiftCard | X91: =IF(W91="","Card",W91) -> GiftCard
A92: 120090 | B92: 102 | C92: 45796 | D92: 0.47458333 | E92: 45796 | F92: =TEXT(Table1[[#This Row],[Business_Day]],"dddd") -> Monday | G92: Morning | H92: Drive-Thru | I92: =IF(H92="","Unknown",H92) -> Drive-Thru | J92: Coffee | K92: Extra Ice | L92: =IF(K92="","No Modifier",K92) -> Extra Ice | M92: 1 | N92: 1.91 | O92: =(V92-T92+R92)/M92 -> 1.91 | P92: =PRODUCT(M92,O92) -> 1.91 | Q92: 0 | R92: =IF(ISBLANK(Q92),ROUND((M92*O92)+T92-V92,2),Q92) -> 0 | S92: 0.13 | T92: =IF(S92="",V92-P92+R92,S92) -> 0.13 | U92: 2.04 | V92: =IF(U92="",(M92*O92)-R92+T92,U92) -> 2.04 | W92: Card | X92: =IF(W92="","Card",W92) -> Card
A93: 120091 | B93: 103 | C93: 45829 | D93: 0.47001157 | E93: 45829 | F93: =TEXT(Table1[[#This Row],[Business_Day]],"dddd") -> Saturday | G93: Lunch | H93: Dine-In | I93: =IF(H93="","Unknown",H93) -> Dine-In | J93: Iced Tea | L93: =IF(K93="","No Modifier",K93) -> No Modifier | M93: 2 | N93: 2.02 | O93: =(V93-T93+R93)/M93 -> 2.02 | P93: =PRODUCT(M93,O93) -> 4.04 | Q93: 0 | R93: =IF(ISBLANK(Q93),ROUND((M93*O93)+T93-V93,2),Q93) -> 0 | S93: 0.26 | T93: =IF(S93="",V93-P93+R93,S93) -> 0.26 | U93: 4.3 | V93: =IF(U93="",(M93*O93)-R93+T93,U93) -> 4.3 | W93: Card | X93: =IF(W93="","Card",W93) -> Card
A94: 120092 | B94: 301 | C94: 45788 | D94: 0.14969907 | E94: 45788 | F94: =TEXT(Table1[[#This Row],[Business_Day]],"dddd") -> Sunday | G94: Afternoon | H94: Dine-In | I94: =IF(H94="","Unknown",H94) -> Dine-In | J94: Chicken Nuggets (10pc) | L94: =IF(K94="","No Modifier",K94) -> No Modifier | M94: 2 | N94: 4.76 | O94: =(V94-T94+R94)/M94 -> 4.76 | P94: =PRODUCT(M94,O94) -> 9.52 | Q94: 0 | R94: =IF(ISBLANK(Q94),ROUND((M94*O94)+T94-V94,2),Q94) -> 0 | S94: 0.76 | T94: =IF(S94="",V94-P94+R94,S94) -> 0.76 | U94: 10.28 | V94: =IF(U94="",(M94*O94)-R94+T94,U94) -> 10.28 | W94: Card | X94: =IF(W94="","Card",W94) -> Card
A95: 120093 | B95: 101 | C95: 45805 | D95: 0.062395833 | E95: 45805 | F95: =TEXT(Table1[[#This Row],[Business_Day]],"dddd") -> Wednesday | G95: Lunch | H95: Drive-Thru | I95: =IF(H95="","Unknown",H95) -> Drive-Thru | J95: Onion Rings | L95: =IF(K95="","No Modifier",K95) -> No Modifier | M95: 1 | N95: 3.05 | O95: =(V95-T95+R95)/M95 -> 3.05 | P95: =PRODUCT(M95,O95) -> 3.05 | Q95: 0 | R95: =IF(ISBLANK(Q95),ROUND((M95*O95)+T95-V95,2),Q95) -> 0 | S95: 0.27 | T95: =IF(S95="",V95-P95+R95,S95) -> 0.27 | U95: 3.32 | V95: =IF(U95="",(M95*O95)-R95+T95,U95) -> 3.32 | W95: Card | X95: =IF(W95="","Card",W95) -> Card
A96: 120094 | B96: 102 | C96: 45791 | D96: 0.04787037 | E96: 45791 | F96: =TEXT(Table1[[#This Row],[Business_Day]],"dddd") -> Wednesday | G96: Lunch | H96: Drive-Thru | I96: =IF(H96="","Unknown",H96) -> Drive-Thru | J96: Chicken Sandwich Combo | K96: No Onions | L96: =IF(K96="","No Modifier",K96) -> No Onions | M96: 1 | N96: 8.79 | O96: =(V96-T96+R96)/M96 -> 8.79 | P96: =PRODUCT(M96,O96) -> 8.79 | Q96: 0 | R96: =IF(ISBLANK(Q96),ROUND((M96*O96)+T96-V96,2),Q96) -> 0 | S96: 0.53 | T96: =IF(S96="",V96-P96+R96,S96) -> 0.53 | U96: 9.32 | V96: =IF(U96="",(M96*O96)-R96+T96,U96) -> 9.32 | W96: Card | X96: =IF(W96="","Card",W96) -> Card
A97: 120095 | B97: 201 | C97: 45758 | D97: 0.079224537 | E97: 45758 | F97: =TEXT(Table1[[#This Row],[Business_Day]],"dddd") -> Friday | G97: Lunch | H97: Dine-In | I97: =IF(H97="","Unknown",H97) -> Dine-In | J97: Chicken Sandwich Combo | L97: =IF(K97="","No Modifier",K97) -> No Modifier | M97: 1 | N97: 8.26 | O97: =(V97-T97+R97)/M97 -> 8.26 | P97: =PRODUCT(M97,O97) -> 8.26 | Q97: 0 | R97: =IF(ISBLANK(Q97),ROUND((M97*O97)+T97-V97,2),Q97) -> 0 | S97: 0.78 | T97: =IF(S97="",V97-P97+R97,S97) -> 0.78 | U97: 9.04 | V97: =IF(U97="",(M97*O97)-R97+T97,U97) -> 9.04 | W97: Cash | X97: =IF(W97="","Card",W97) -> Cash
A98: 120096 | B98: 501 | C98: 45760 | D98: 0.49508102 | E98: 45760 | F98: =TEXT(Table1[[#This Row],[Business_Day]],"dddd") -> Sunday | G98: Lunch | H98: Dine-In | I98: =IF(H98="","Unknown",H98) -> Dine-In | J98: Chicken Sandwich Combo | K98: Add Bacon | L98: =IF(K98="","No Modifier",K98) -> Add Bacon | M98: 1 | N98: 9.14 | O98: =(V98-T98+R98)/M98 -> 10.14 | P98: =PRODUCT(M98,O98) -> 10.14 | Q98: 0 | R98: =IF(ISBLANK(Q98),ROUND((M98*O98)+T98-V98,2),Q98) -> 0 | S98: 0.61 | T98: =IF(S98="",V98-P98+R98,S98) -> 0.61 | U98: 10.75 | V98: =IF(U98="",(M98*O98)-R98+T98,U98) -> 10.75 | W98: Card | X98: =IF(W98="","Card",W98) -> Card
A99: 120097 | B99: 401 | C99: 45869 | D99: 0.46560185 | E99: 45869 | F99: =TEXT(Table1[[#This Row],[Business_Day]],"dddd") -> Thursday | G99: Lunch | H99: Takeout | I99: =IF(H99="","Unknown",H99) -> Takeout | J99: Spicy Chicken Sandwich | L99: =IF(K99="","No Modifier",K99) -> No Modifier | M99: 2 | N99: 5.74 | O99: =(V99-T99+R99)/M99 -> 5.74 | P99: =PRODUCT(M99,O99) -> 11.48 | Q99: 0 | R99: =IF(ISBLANK(Q99),ROUND((M99*O99)+T99-V99,2),Q99) -> 0 | S99: 0.92 | T99: =IF(S99="",V99-P99+R99,S99) -> 0.92 | U99: 12.4 | V99: =IF(U99="",(M99*O99)-R99+T99,U99) -> 12.4 | W99: Card | X99: =IF(W99="","Card",W99) -> Card
A100: 120098 | B100: 402 | C100: 45821 | D100: 0.25631944 | E100: 45821 | F100: =TEXT(Table1[[#This Row],[Business_Day]],"dddd") -> Friday | G100: Breakfast | H100: Dine-In | I100: =IF(H100="","Unknown",H100) -> Dine-In | J100: Latte | K100: Light Ice | L100: =IF(K100="","No Modifier",K100) -> Light Ice | M100: 1 | N100: 3.24 | O100: =(V100-T100+R100)/M100 -> 3.24 | P100: =PRODUCT(M100,O100) -> 3.24 | Q100: 0 | R100: =IF(ISBLANK(Q100),ROUND((M100*O100)+T100-V100,2),Q100) -> 0 | S100: 0.26 | T100: =IF(S100="",V100-P100+R100,S100) -> 0.26 | U100: 3.5 | V100: =IF(U100="",(M100*O100)-R100+T100,U100) -> 3.5 | W100: MobilePay | X100: =IF(W100="","Card",W100) -> MobilePay
...

Sheet Cleaned
A1: Order_ID | B1: Store_ID | C1: Transaction_Date | D1: Time | E1: Business_Day | F1: Day_Of_Week | G1: Day_Part | H1: Service_Mode | I1: Menu_Item | J1: Modifier | K1: Payment_Type | L1: Quantity | M1: Unit_Price | N1: Gross_Amount | O1: Discount | P1: Tax | Q1: Total_Amount
A2: 120000 | B2: =_xlfn.XLOOKUP(A2,Cleaning!$A:$A,Cleaning!$B:$B,0,0) -> 102 | C2: =_xlfn.XLOOKUP(A2,Cleaning!$A:$A,Cleaning!$C:$C,0,0) -> 45843 | D2: =_xlfn.XLOOKUP(A2,Cleaning!$A:$A,Cleaning!$D:$D,0,0) -> 0.25981481 | E2: =_xlfn.XLOOKUP(A2,Cleaning!$A:$A,Cleaning!$E:$E,0,0) -> 45843 | F2: =_xlfn.XLOOKUP(A2,Cleaning!$A:$A,Cleaning!$F:$F,0,0) -> Saturday | G2: =_xlfn.XLOOKUP(A2,Cleaning!$A:$A,Cleaning!$G:$G,0,0) -> Breakfast | H2: =_xlfn.XLOOKUP(A2,Cleaning!$A:$A,Cleaning!$I:$I,0,0) -> Drive-Thru | I2: =_xlfn.XLOOKUP(A2,Cleaning!$A:$A,Cleaning!$J:$J,0,0) -> Bottled Water | J2: =_xlfn.XLOOKUP(A2,Cleaning!$A:$A,Cleaning!$L:$L,0,0) -> No Modifier | K2: =_xlfn.XLOOKUP(A2,Cleaning!$A:$A,Cleaning!$X:$X,0,0) -> Cash | L2: =_xlfn.XLOOKUP(A2,Cleaning!$A:$A,Cleaning!$M:$M,0,0) -> 1 | M2: =_xlfn.XLOOKUP(A2,Cleaning!$A:$A,Cleaning!$O:$O,0,0) -> 1.48 | N2: =_xlfn.XLOOKUP(A2,Cleaning!$A:$A,Cleaning!$P:$P,0,0) -> 1.48 | O2: =_xlfn.XLOOKUP(A2,Cleaning!$A:$A,Cleaning!$R:$R,0,0) -> 0.15 | P2: =_xlfn.XLOOKUP(A2,Cleaning!$A:$A,Cleaning!$T:$T,0,0) -> 0.1 | Q2: =_xlfn.XLOOKUP(A2,Cleaning!$A:$A,Cleaning!$V:$V,0,0) -> 1.43
A3: 120001 | B3: =_xlfn.XLOOKUP(A3,Cleaning!$A:$A,Cleaning!$B:$B,0,0) -> 201 | C3: =_xlfn.XLOOKUP(A3,Cleaning!$A:$A,Cleaning!$C:$C,0,0) -> 45843 | D3: =_xlfn.XLOOKUP(A3,Cleaning!$A:$A,Cleaning!$D:$D,0,0) -> 0.49225694 | E3: =_xlfn.XLOOKUP(A3,Cleaning!$A:$A,Cleaning!$E:$E,0,0) -> 45843 | F3: =_xlfn.XLOOKUP(A3,Cleaning!$A:$A,Cleaning!$F:$F,0,0) -> Saturday | G3: =_xlfn.XLOOKUP(A3,Cleaning!$A:$A,Cleaning!$G:$G,0,0) -> Lunch | H3: =_xlfn.XLOOKUP(A3,Cleaning!$A:$A,Cleaning!$I:$I,0,0) -> Dine-In | I3: =_xlfn.XLOOKUP(A3,Cleaning!$A:$A,Cleaning!$J:$J,0,0) -> Chicken Sandwich | J3: =_xlfn.XLOOKUP(A3,Cleaning!$A:$A,Cleaning!$L:$L,0,0) -> No Modifier | K3: =_xlfn.XLOOKUP(A3,Cleaning!$A:$A,Cleaning!$X:$X,0,0) -> Card | L3: =_xlfn.XLOOKUP(A3,Cleaning!$A:$A,Cleaning!$M:$M,0,0) -> 1 | M3: =_xlfn.XLOOKUP(A3,Cleaning!$A:$A,Cleaning!$O:$O,0,0) -> 5.34 | N3: =_xlfn.XLOOKUP(A3,Cleaning!$A:$A,Cleaning!$P:$P,0,0) -> 5.34 | O3: =_xlfn.XLOOKUP(A3,Cleaning!$A:$A,Cleaning!$R:$R,0,0) -> 0 | P3: =_xlfn.XLOOKUP(A3,Cleaning!$A:$A,Cleaning!$T:$T,0,0) -> 0.45 | Q3: =_xlfn.XLOOKUP(A3,Cleaning!$A:$A,Cleaning!$V:$V,0,0) -> 5.79
A4: 120002 | B4: =_xlfn.XLOOKUP(A4,Cleaning!$A:$A,Cleaning!$B:$B,0,0) -> 403 | C4: =_xlfn.XLOOKUP(A4,Cleaning!$A:$A,Cleaning!$C:$C,0,0) -> 45760 | D4: =_xlfn.XLOOKUP(A4,Cleaning!$A:$A,Cleaning!$D:$D,0,0) -> 0.33721065 | E4: =_xlfn.XLOOKUP(A4,Cleaning!$A:$A,Cleaning!$E:$E,0,0) -> 45760 | F4: =_xlfn.XLOOKUP(A4,Cleaning!$A:$A,Cleaning!$F:$F,0,0) -> Sunday | G4: =_xlfn.XLOOKUP(A4,Cleaning!$A:$A,Cleaning!$G:$G,0,0) -> Breakfast | H4: =_xlfn.XLOOKUP(A4,Cleaning!$A:$A,Cleaning!$I:$I,0,0) -> Takeout | I4: =_xlfn.XLOOKUP(A4,Cleaning!$A:$A,Cleaning!$J:$J,0,0) -> Bottled Water | J4: =_xlfn.XLOOKUP(A4,Cleaning!$A:$A,Cleaning!$L:$L,0,0) -> Light Ice | K4: =_xlfn.XLOOKUP(A4,Cleaning!$A:$A,Cleaning!$X:$X,0,0) -> Cash | L4: =_xlfn.XLOOKUP(A4,Cleaning!$A:$A,Cleaning!$M:$M,0,0) -> 1 | M4: =_xlfn.XLOOKUP(A4,Cleaning!$A:$A,Cleaning!$O:$O,0,0) -> 1.49 | N4: =_xlfn.XLOOKUP(A4,Cleaning!$A:$A,Cleaning!$P:$P,0,0) -> 1.49 | O4: =_xlfn.XLOOKUP(A4,Cleaning!$A:$A,Cleaning!$R:$R,0,0) -> 0.15 | P4: =_xlfn.XLOOKUP(A4,Cleaning!$A:$A,Cleaning!$T:$T,0,0) -> 0.1 | Q4: =_xlfn.XLOOKUP(A4,Cleaning!$A:$A,Cleaning!$V:$V,0,0) -> 1.44
A5: 120003 | B5: =_xlfn.XLOOKUP(A5,Cleaning!$A:$A,Cleaning!$B:$B,0,0) -> 301 | C5: =_xlfn.XLOOKUP(A5,Cleaning!$A:$A,Cleaning!$C:$C,0,0) -> 45833 | D5: =_xlfn.XLOOKUP(A5,Cleaning!$A:$A,Cleaning!$D:$D,0,0) -> 0.27936343 | E5: =_xlfn.XLOOKUP(A5,Cleaning!$A:$A,Cleaning!$E:$E,0,0) -> 45833 | F5: =_xlfn.XLOOKUP(A5,Cleaning!$A:$A,Cleaning!$F:$F,0,0) -> Wednesday | G5: =_xlfn.XLOOKUP(A5,Cleaning!$A:$A,Cleaning!$G:$G,0,0) -> Breakfast | H5: =_xlfn.XLOOKUP(A5,Cleaning!$A:$A,Cleaning!$I:$I,0,0) -> Drive-Thru | I5: =_xlfn.XLOOKUP(A5,Cleaning!$A:$A,Cleaning!$J:$J,0,0) -> Egg Muffin | J5: =_xlfn.XLOOKUP(A5,Cleaning!$A:$A,Cleaning!$L:$L,0,0) -> No Cheese | K5: =_xlfn.XLOOKUP(A5,Cleaning!$A:$A,Cleaning!$X:$X,0,0) -> Cash | L5: =_xlfn.XLOOKUP(A5,Cleaning!$A:$A,Cleaning!$M:$M,0,0) -> 1 | M5: =_xlfn.XLOOKUP(A5,Cleaning!$A:$A,Cleaning!$O:$O,0,0) -> 3.62 | N5: =_xlfn.XLOOKUP(A5,Cleaning!$A:$A,Cleaning!$P:$P,0,0) -> 3.62 | O5: =_xlfn.XLOOKUP(A5,Cleaning!$A:$A,Cleaning!$R:$R,0,0) -> 0 | P5: =_xlfn.XLOOKUP(A5,Cleaning!$A:$A,Cleaning!$T:$T,0,0) -> 0.34 | Q5: =_xlfn.XLOOKUP(A5,Cleaning!$A:$A,Cleaning!$V:$V,0,0) -> 3.96
A6: 120004 | B6: =_xlfn.XLOOKUP(A6,Cleaning!$A:$A,Cleaning!$B:$B,0,0) -> 301 | C6: =_xlfn.XLOOKUP(A6,Cleaning!$A:$A,Cleaning!$C:$C,0,0) -> 45870 | D6: =_xlfn.XLOOKUP(A6,Cleaning!$A:$A,Cleaning!$D:$D,0,0) -> 0.54069444 | E6: =_xlfn.XLOOKUP(A6,Cleaning!$A:$A,Cleaning!$E:$E,0,0) -> 45870 | F6: =_xlfn.XLOOKUP(A6,Cleaning!$A:$A,Cleaning!$F:$F,0,0) -> Friday | G6: =_xlfn.XLOOKUP(A6,Cleaning!$A:$A,Cleaning!$G:$G,0,0) -> Lunch | H6: =_xlfn.XLOOKUP(A6,Cleaning!$A:$A,Cleaning!$I:$I,0,0) -> Drive-Thru | I6: =_xlfn.XLOOKUP(A6,Cleaning!$A:$A,Cleaning!$J:$J,0,0) -> Spicy Chicken Combo | J6: =_xlfn.XLOOKUP(A6,Cleaning!$A:$A,Cleaning!$L:$L,0,0) -> No Modifier | K6: =_xlfn.XLOOKUP(A6,Cleaning!$A:$A,Cleaning!$X:$X,0,0) -> Card | L6: =_xlfn.XLOOKUP(A6,Cleaning!$A:$A,Cleaning!$M:$M,0,0) -> 2 | M6: =_xlfn.XLOOKUP(A6,Cleaning!$A:$A,Cleaning!$O:$O,0,0) -> 9.17 | N6: =_xlfn.XLOOKUP(A6,Cleaning!$A:$A,Cleaning!$P:$P,0,0) -> 18.34 | O6: =_xlfn.XLOOKUP(A6,Cleaning!$A:$A,Cleaning!$R:$R,0,0) -> 0 | P6: =_xlfn.XLOOKUP(A6,Cleaning!$A:$A,Cleaning!$T:$T,0,0) -> 1.38 | Q6: =_xlfn.XLOOKUP(A6,Cleaning!$A:$A,Cleaning!$V:$V,0,0) -> 19.72
A7: 120005 | B7: =_xlfn.XLOOKUP(A7,Cleaning!$A:$A,Cleaning!$B:$B,0,0) -> 501 | C7: =_xlfn.XLOOKUP(A7,Cleaning!$A:$A,Cleaning!$C:$C,0,0) -> 45850 | D7: =_xlfn.XLOOKUP(A7,Cleaning!$A:$A,Cleaning!$D:$D,0,0) -> 0.52258102 | E7: =_xlfn.XLOOKUP(A7,Cleaning!$A:$A,Cleaning!$E:$E,0,0) -> 45850 | F7: =_xlfn.XLOOKUP(A7,Cleaning!$A:$A,Cleaning!$F:$F,0,0) -> Saturday | G7: =_xlfn.XLOOKUP(A7,Cleaning!$A:$A,Cleaning!$G:$G,0,0) -> Lunch | H7: =_xlfn.XLOOKUP(A7,Cleaning!$A:$A,Cleaning!$I:$I,0,0) -> Dine-In | I7: =_xlfn.XLOOKUP(A7,Cleaning!$A:$A,Cleaning!$J:$J,0,0) -> Double Cheeseburger | J7: =_xlfn.XLOOKUP(A7,Cleaning!$A:$A,Cleaning!$L:$L,0,0) -> No Modifier | K7: =_xlfn.XLOOKUP(A7,Cleaning!$A:$A,Cleaning!$X:$X,0,0) -> Card | L7: =_xlfn.XLOOKUP(A7,Cleaning!$A:$A,Cleaning!$M:$M,0,0) -> 1 | M7: =_xlfn.XLOOKUP(A7,Cleaning!$A:$A,Cleaning!$O:$O,0,0) -> 5.64 | N7: =_xlfn.XLOOKUP(A7,Cleaning!$A:$A,Cleaning!$P:$P,0,0) -> 5.64 | O7: =_xlfn.XLOOKUP(A7,Cleaning!$A:$A,Cleaning!$R:$R,0,0) -> 0 | P7: =_xlfn.XLOOKUP(A7,Cleaning!$A:$A,Cleaning!$T:$T,0,0) -> 0.37 | Q7: =_xlfn.XLOOKUP(A7,Cleaning!$A:$A,Cleaning!$V:$V,0,0) -> 6.01
A8: 120006 | B8: =_xlfn.XLOOKUP(A8,Cleaning!$A:$A,Cleaning!$B:$B,0,0) -> 101 | C8: =_xlfn.XLOOKUP(A8,Cleaning!$A:$A,Cleaning!$C:$C,0,0) -> 45864 | D8: =_xlfn.XLOOKUP(A8,Cleaning!$A:$A,Cleaning!$D:$D,0,0) -> 0.24761574 | E8: =_xlfn.XLOOKUP(A8,Cleaning!$A:$A,Cleaning!$E:$E,0,0) -> 45864 | F8: =_xlfn.XLOOKUP(A8,Cleaning!$A:$A,Cleaning!$F:$F,0,0) -> Saturday | G8: =_xlfn.XLOOKUP(A8,Cleaning!$A:$A,Cleaning!$G:$G,0,0) -> Afternoon | H8: =_xlfn.XLOOKUP(A8,Cleaning!$A:$A,Cleaning!$I:$I,0,0) -> Delivery | I8: =_xlfn.XLOOKUP(A8,Cleaning!$A:$A,Cleaning!$J:$J,0,0) -> Onion Rings | J8: =_xlfn.XLOOKUP(A8,Cleaning!$A:$A,Cleaning!$L:$L,0,0) -> No Modifier | K8: =_xlfn.XLOOKUP(A8,Cleaning!$A:$A,Cleaning!$X:$X,0,0) -> MobilePay | L8: =_xlfn.XLOOKUP(A8,Cleaning!$A:$A,Cleaning!$M:$M,0,0) -> 1 | M8: =_xlfn.XLOOKUP(A8,Cleaning!$A:$A,Cleaning!$O:$O,0,0) -> 3.59 | N8: =_xlfn.XLOOKUP(A8,Cleaning!$A:$A,Cleaning!$P:$P,0,0) -> 3.59 | O8: =_xlfn.XLOOKUP(A8,Cleaning!$A:$A,Cleaning!$R:$R,0,0) -> 0.54 | P8: =_xlfn.XLOOKUP(A8,Cleaning!$A:$A,Cleaning!$T:$T,0,0) -> 0.29 | Q8: =_xlfn.XLOOKUP(A8,Cleaning!$A:$A,Cleaning!$V:$V,0,0) -> 3.34
A9: 120007 | B9: =_xlfn.XLOOKUP(A9,Cleaning!$A:$A,Cleaning!$B:$B,0,0) -> 403 | C9: =_xlfn.XLOOKUP(A9,Cleaning!$A:$A,Cleaning!$C:$C,0,0) -> 45859 | D9: =_xlfn.XLOOKUP(A9,Cleaning!$A:$A,Cleaning!$D:$D,0,0) -> 0.20011574 | E9: =_xlfn.XLOOKUP(A9,Cleaning!$A:$A,Cleaning!$E:$E,0,0) -> 45859 | F9: =_xlfn.XLOOKUP(A9,Cleaning!$A:$A,Cleaning!$F:$F,0,0) -> Monday | G9: =_xlfn.XLOOKUP(A9,Cleaning!$A:$A,Cleaning!$G:$G,0,0) -> Afternoon | H9: =_xlfn.XLOOKUP(A9,Cleaning!$A:$A,Cleaning!$I:$I,0,0) -> Takeout | I9: =_xlfn.XLOOKUP(A9,Cleaning!$A:$A,Cleaning!$J:$J,0,0) -> Soft Drink (Medium) | J9: =_xlfn.XLOOKUP(A9,Cleaning!$A:$A,Cleaning!$L:$L,0,0) -> No Modifier | K9: =_xlfn.XLOOKUP(A9,Cleaning!$A:$A,Cleaning!$X:$X,0,0) -> Cash | L9: =_xlfn.XLOOKUP(A9,Cleaning!$A:$A,Cleaning!$M:$M,0,0) -> 1 | M9: =_xlfn.XLOOKUP(A9,Cleaning!$A:$A,Cleaning!$O:$O,0,0) -> 1.8 | N9: =_xlfn.XLOOKUP(A9,Cleaning!$A:$A,Cleaning!$P:$P,0,0) -> 1.8 | O9: =_xlfn.XLOOKUP(A9,Cleaning!$A:$A,Cleaning!$R:$R,0,0) -> 0.27 | P9: =_xlfn.XLOOKUP(A9,Cleaning!$A:$A,Cleaning!$T:$T,0,0) -> 0.11 | Q9: =_xlfn.XLOOKUP(A9,Cleaning!$A:$A,Cleaning!$V:$V,0,0) -> 1.64
A10: 120008 | B10: =_xlfn.XLOOKUP(A10,Cleaning!$A:$A,Cleaning!$B:$B,0,0) -> 102 | C10: =_xlfn.XLOOKUP(A10,Cleaning!$A:$A,Cleaning!$C:$C,0,0) -> 45810 | D10: =_xlfn.XLOOKUP(A10,Cleaning!$A:$A,Cleaning!$D:$D,0,0) -> 0.464375 | E10: =_xlfn.XLOOKUP(A10,Cleaning!$A:$A,Cleaning!$E:$E,0,0) -> 45810 | F10: =_xlfn.XLOOKUP(A10,Cleaning!$A:$A,Cleaning!$F:$F,0,0) -> Monday | G10: =_xlfn.XLOOKUP(A10,Cleaning!$A:$A,Cleaning!$G:$G,0,0) -> Late Night | H10: =_xlfn.XLOOKUP(A10,Cleaning!$A:$A,Cleaning!$I:$I,0,0) -> Delivery | I10: =_xlfn.XLOOKUP(A10,Cleaning!$A:$A,Cleaning!$J:$J,0,0) -> Chicken Sandwich | J10: =_xlfn.XLOOKUP(A10,Cleaning!$A:$A,Cleaning!$L:$L,0,0) -> Extra Sauce | K10: =_xlfn.XLOOKUP(A10,Cleaning!$A:$A,Cleaning!$X:$X,0,0) -> Card | L10: =_xlfn.XLOOKUP(A10,Cleaning!$A:$A,Cleaning!$M:$M,0,0) -> 2 | M10: =_xlfn.XLOOKUP(A10,Cleaning!$A:$A,Cleaning!$O:$O,0,0) -> 5.47 | N10: =_xlfn.XLOOKUP(A10,Cleaning!$A:$A,Cleaning!$P:$P,0,0) -> 10.94 | O10: =_xlfn.XLOOKUP(A10,Cleaning!$A:$A,Cleaning!$R:$R,0,0) -> 0 | P10: =_xlfn.XLOOKUP(A10,Cleaning!$A:$A,Cleaning!$T:$T,0,0) -> 0.79 | Q10: =_xlfn.XLOOKUP(A10,Cleaning!$A:$A,Cleaning!$V:$V,0,0) -> 11.73
A11: 120009 | B11: =_xlfn.XLOOKUP(A11,Cleaning!$A:$A,Cleaning!$B:$B,0,0) -> 402 | C11: =_xlfn.XLOOKUP(A11,Cleaning!$A:$A,Cleaning!$C:$C,0,0) -> 45850 | D11: =_xlfn.XLOOKUP(A11,Cleaning!$A:$A,Cleaning!$D:$D,0,0) -> 0.22292824 | E11: =_xlfn.XLOOKUP(A11,Cleaning!$A:$A,Cleaning!$E:$E,0,0) -> 45850 | F11: =_xlfn.XLOOKUP(A11,Cleaning!$A:$A,Cleaning!$F:$F,0,0) -> Saturday | G11: =_xlfn.XLOOKUP(A11,Cleaning!$A:$A,Cleaning!$G:$G,0,0) -> Breakfast | H11: =_xlfn.XLOOKUP(A11,Cleaning!$A:$A,Cleaning!$I:$I,0,0) -> Drive-Thru | I11: =_xlfn.XLOOKUP(A11,Cleaning!$A:$A,Cleaning!$J:$J,0,0) -> Hash Browns | J11: =_xlfn.XLOOKUP(A11,Cleaning!$A:$A,Cleaning!$L:$L,0,0) -> No Modifier | K11: =_xlfn.XLOOKUP(A11,Cleaning!$A:$A,Cleaning!$X:$X,0,0) -> Card | L11: =_xlfn.XLOOKUP(A11,Cleaning!$A:$A,Cleaning!$M:$M,0,0) -> 1 | M11: =_xlfn.XLOOKUP(A11,Cleaning!$A:$A,Cleaning!$O:$O,0,0) -> 2 | N11: =_xlfn.XLOOKUP(A11,Cleaning!$A:$A,Cleaning!$P:$P,0,0) -> 2 | O11: =_xlfn.XLOOKUP(A11,Cleaning!$A:$A,Cleaning!$R:$R,0,0) -> 0 | P11: =_xlfn.XLOOKUP(A11,Cleaning!$A:$A,Cleaning!$T:$T,0,0) -> 0.12 | Q11: =_xlfn.XLOOKUP(A11,Cleaning!$A:$A,Cleaning!$V:$V,0,0) -> 2.12
A12: 120010 | B12: =_xlfn.XLOOKUP(A12,Cleaning!$A:$A,Cleaning!$B:$B,0,0) -> 103 | C12: =_xlfn.XLOOKUP(A12,Cleaning!$A:$A,Cleaning!$C:$C,0,0) -> 45766 | D12: =_xlfn.XLOOKUP(A12,Cleaning!$A:$A,Cleaning!$D:$D,0,0) -> 0.38599537 | E12: =_xlfn.XLOOKUP(A12,Cleaning!$A:$A,Cleaning!$E:$E,0,0) -> 45766 | F12: =_xlfn.XLOOKUP(A12,Cleaning!$A:$A,Cleaning!$F:$F,0,0) -> Saturday | G12: =_xlfn.XLOOKUP(A12,Cleaning!$A:$A,Cleaning!$G:$G,0,0) -> Dinner | H12: =_xlfn.XLOOKUP(A12,Cleaning!$A:$A,Cleaning!$I:$I,0,0) -> Takeout | I12: =_xlfn.XLOOKUP(A12,Cleaning!$A:$A,Cleaning!$J:$J,0,0) -> Double Cheeseburger | J12: =_xlfn.XLOOKUP(A12,Cleaning!$A:$A,Cleaning!$L:$L,0,0) -> No Modifier | K12: =_xlfn.XLOOKUP(A12,Cleaning!$A:$A,Cleaning!$X:$X,0,0) -> Card | L12: =_xlfn.XLOOKUP(A12,Cleaning!$A:$A,Cleaning!$M:$M,0,0) -> 1 | M12: =_xlfn.XLOOKUP(A12,Cleaning!$A:$A,Cleaning!$O:$O,0,0) -> 5.55 | N12: =_xlfn.XLOOKUP(A12,Cleaning!$A:$A,Cleaning!$P:$P,0,0) -> 5.55 | O12: =_xlfn.XLOOKUP(A12,Cleaning!$A:$A,Cleaning!$R:$R,0,0) -> 0 | P12: =_xlfn.XLOOKUP(A12,Cleaning!$A:$A,Cleaning!$T:$T,0,0) -> 0.33 | Q12: =_xlfn.XLOOKUP(A12,Cleaning!$A:$A,Cleaning!$V:$V,0,0) -> 5.88
A13: 120011 | B13: =_xlfn.XLOOKUP(A13,Cleaning!$A:$A,Cleaning!$B:$B,0,0) -> 102 | C13: =_xlfn.XLOOKUP(A13,Cleaning!$A:$A,Cleaning!$C:$C,0,0) -> 45854 | D13: =_xlfn.XLOOKUP(A13,Cleaning!$A:$A,Cleaning!$D:$D,0,0) -> 0.46420139 | E13: =_xlfn.XLOOKUP(A13,Cleaning!$A:$A,Cleaning!$E:$E,0,0) -> 45854 | F13: =_xlfn.XLOOKUP(A13,Cleaning!$A:$A,Cleaning!$F:$F,0,0) -> Wednesday | G13: =_xlfn.XLOOKUP(A13,Cleaning!$A:$A,Cleaning!$G:$G,0,0) -> Morning | H13: =_xlfn.XLOOKUP(A13,Cleaning!$A:$A,Cleaning!$I:$I,0,0) -> Dine-In | I13: =_xlfn.XLOOKUP(A13,Cleaning!$A:$A,Cleaning!$J:$J,0,0) -> Apple Pie | J13: =_xlfn.XLOOKUP(A13,Cleaning!$A:$A,Cleaning!$L:$L,0,0) -> No Modifier | K13: =_xlfn.XLOOKUP(A13,Cleaning!$A:$A,Cleaning!$X:$X,0,0) -> Card | L13: =_xlfn.XLOOKUP(A13,Cleaning!$A:$A,Cleaning!$M:$M,0,0) -> 1 | M13: =_xlfn.XLOOKUP(A13,Cleaning!$A:$A,Cleaning!$O:$O,0,0) -> 1.53 | N13: =_xlfn.XLOOKUP(A13,Cleaning!$A:$A,Cleaning!$P:$P,0,0) -> 1.53 | O13: =_xlfn.XLOOKUP(A13,Cleaning!$A:$A,Cleaning!$R:$R,0,0) -> 0 | P13: =_xlfn.XLOOKUP(A13,Cleaning!$A:$A,Cleaning!$T:$T,0,0) -> 0.1 | Q13: =_xlfn.XLOOKUP(A13,Cleaning!$A:$A,Cleaning!$V:$V,0,0) -> 1.63
... A1744: 121742 | B1744: =_xlfn.XLOOKUP(A1744,Cleaning!$A:$A,Cleaning!$B:$B,0,0) -> 301 | C1744: =_xlfn.XLOOKUP(A1744,Cleaning!$A:$A,Cleaning!$C:$C,0,0) -> 45767 | D1744: =_xlfn.XLOOKUP(A1744,Cleaning!$A:$A,Cleaning!$D:$D,0,0) -> 0.4678125 | E1744: =_xlfn.XLOOKUP(A1744,Cleaning!$A:$A,Cleaning!$E:$E,0,0) -> 45767 | F1744: =_xlfn.XLOOKUP(A1744,Cleaning!$A:$A,Cleaning!$F:$F,0,0) -> Sunday | G1744: =_xlfn.XLOOKUP(A1744,Cleaning!$A:$A,Cleaning!$G:$G,0,0) -> Lunch | H1744: =_xlfn.XLOOKUP(A1744,Cleaning!$A:$A,Cleaning!$I:$I,0,0) -> Drive-Thru | I1744: =_xlfn.XLOOKUP(A1744,Cleaning!$A:$A,Cleaning!$J:$J,0,0) -> Soft Drink (Medium) | J1744: =_xlfn.XLOOKUP(A1744,Cleaning!$A:$A,Cleaning!$L:$L,0,0) -> Light Ice | K1744: =_xlfn.XLOOKUP(A1744,Cleaning!$A:$A,Cleaning!$X:$X,0,0) -> MobilePay | L1744: =_xlfn.XLOOKUP(A1744,Cleaning!$A:$A,Cleaning!$M:$M,0,0) -> 3 | M1744: =_xlfn.XLOOKUP(A1744,Cleaning!$A:$A,Cleaning!$O:$O,0,0) -> 1.75 | N1744: =_xlfn.XLOOKUP(A1744,Cleaning!$A:$A,Cleaning!$P:$P,0,0) -> 5.25 | O1744: =_xlfn.XLOOKUP(A1744,Cleaning!$A:$A,Cleaning!$R:$R,0,0) -> 0 | P1744: =_xlfn.XLOOKUP(A1744,Cleaning!$A:$A,Cleaning!$T:$T,0,0) -> 0.37 | Q1744: =_xlfn.XLOOKUP(A1744,Cleaning!$A:$A,Cleaning!$V:$V,0,0) -> 5.62

Sheet Pivot_Table
A1: Menu_Item | B1: (All) | E1: Service_Mode | F1: Sum of Quantity
E2: Delivery | F2: 303
A3: Count of Order_ID | B3: Sum of Total_Amount | E3: Dine-In | F3: 662
A4: 1743 | B4: 11641.64 | E4: Drive-Thru | F4: 641
E5: Takeout | F5: 591
E6: Unknown | F6: 17
A7: Quantity | B7: Sum of Total_Amount | C7: Count of Order_ID | E7: Grand Total | F7: 2214
A8: 1 | B8: 7441.64 | C8: 1360
A9: 2 | B9: 3010.23 | C9: 304
A10: 3 | B10: 1050.76 | C10: 70
A11: 4 | B11: 139.01 | C11: 9
A12: Grand Total | B12: 11641.64 | C12: 1743
A15: Payment_Type | B15: Average of Total_Amount
A16: Card | B16: 6.9383749
A17: Cash | B17: 6.2048276
A18: GiftCard | B18: 7.0902198
A19: MobilePay | B19: 6.2427206
